{
"meta":{"test_sets":[],"test_metrics":[],"learn_metrics":[{"best_value":"Min","name":"Logloss"}],"launch_mode":"Train","parameters":"","iteration_count":1000,"learn_sets":["learn"],"name":"experiment"},
"iterations":[
{"learn":[0.6466621709],"iteration":0,"passed_time":0.03431762616,"remaining_time":34.28330854},
{"learn":[0.5992277413],"iteration":1,"passed_time":0.06482031733,"remaining_time":32.34533835},
{"learn":[0.5594588268],"iteration":2,"passed_time":0.09475291588,"remaining_time":31.48955238},
{"learn":[0.5159016267],"iteration":3,"passed_time":0.1255870901,"remaining_time":31.27118544},
{"learn":[0.4921073248],"iteration":4,"passed_time":0.1526259704,"remaining_time":30.37256811},
{"learn":[0.4635546803],"iteration":5,"passed_time":0.1834990263,"remaining_time":30.39967203},
{"learn":[0.4394824993],"iteration":6,"passed_time":0.212522987,"remaining_time":30.14790373},
{"learn":[0.4204622811],"iteration":7,"passed_time":0.2413085517,"remaining_time":29.92226041},
{"learn":[0.3988655113],"iteration":8,"passed_time":0.2717982366,"remaining_time":29.92800583},
{"learn":[0.3808317371],"iteration":9,"passed_time":0.3030546514,"remaining_time":30.00241049},
{"learn":[0.3669772943],"iteration":10,"passed_time":0.333691971,"remaining_time":30.00194175},
{"learn":[0.3505047461],"iteration":11,"passed_time":0.363140377,"remaining_time":29.8985577},
{"learn":[0.3382913248],"iteration":12,"passed_time":0.3926901109,"remaining_time":29.8142415},
{"learn":[0.3249381342],"iteration":13,"passed_time":0.4222270786,"remaining_time":29.73684996},
{"learn":[0.3118960721],"iteration":14,"passed_time":0.4537243251,"remaining_time":29.79456402},
{"learn":[0.3014847577],"iteration":15,"passed_time":0.4842718508,"remaining_time":29.78271882},
{"learn":[0.2913653137],"iteration":16,"passed_time":0.514029786,"remaining_time":29.72301645},
{"learn":[0.2821190717],"iteration":17,"passed_time":0.5422795731,"remaining_time":29.58436338},
{"learn":[0.2735028712],"iteration":18,"passed_time":0.5737126021,"remaining_time":29.62168751},
{"learn":[0.2644456981],"iteration":19,"passed_time":0.606633108,"remaining_time":29.72502229},
{"learn":[0.2595712471],"iteration":20,"passed_time":0.6371422684,"remaining_time":29.70296575},
{"learn":[0.2533454817],"iteration":21,"passed_time":0.6672749599,"remaining_time":29.66340504},
{"learn":[0.2475697669],"iteration":22,"passed_time":0.6965196688,"remaining_time":29.58694419},
{"learn":[0.2429461173],"iteration":23,"passed_time":0.7254955244,"remaining_time":29.50348466},
{"learn":[0.2379429761],"iteration":24,"passed_time":0.7558104633,"remaining_time":29.47660807},
{"learn":[0.2334006838],"iteration":25,"passed_time":0.7866419299,"remaining_time":29.46881691},
{"learn":[0.2280446642],"iteration":26,"passed_time":0.8163236604,"remaining_time":29.41788598},
{"learn":[0.2220966234],"iteration":27,"passed_time":0.8483273097,"remaining_time":29.44907661},
{"learn":[0.2175233138],"iteration":28,"passed_time":0.8780034819,"remaining_time":29.39797865},
{"learn":[0.2136703531],"iteration":29,"passed_time":0.9082738409,"remaining_time":29.36752085},
{"learn":[0.2079354725],"iteration":30,"passed_time":0.9398322923,"remaining_time":29.37733843},
{"learn":[0.2046005591],"iteration":31,"passed_time":0.9716571084,"remaining_time":29.39262753},
{"learn":[0.2015971797],"iteration":32,"passed_time":1.001129423,"remaining_time":29.33612583},
{"learn":[0.1988100198],"iteration":33,"passed_time":1.029443831,"remaining_time":29.24831589},
{"learn":[0.1948192005],"iteration":34,"passed_time":1.059982431,"remaining_time":29.22522987},
{"learn":[0.1917957261],"iteration":35,"passed_time":1.088606662,"remaining_time":29.15046728},
{"learn":[0.1886962115],"iteration":36,"passed_time":1.118933021,"remaining_time":29.12249997},
{"learn":[0.1860673236],"iteration":37,"passed_time":1.149861774,"remaining_time":29.1096586},
{"learn":[0.1836815148],"iteration":38,"passed_time":1.181275977,"remaining_time":29.10785164},
{"learn":[0.1811615631],"iteration":39,"passed_time":1.219592583,"remaining_time":29.270222},
{"learn":[0.1786621109],"iteration":40,"passed_time":1.261517662,"remaining_time":29.5072058},
{"learn":[0.1763454711],"iteration":41,"passed_time":1.296161219,"remaining_time":29.56482019},
{"learn":[0.174149993],"iteration":42,"passed_time":1.327140938,"remaining_time":29.53660181},
{"learn":[0.1716719342],"iteration":43,"passed_time":1.358491027,"remaining_time":29.51630503},
{"learn":[0.1695581201],"iteration":44,"passed_time":1.387966422,"remaining_time":29.45573184},
{"learn":[0.1670911302],"iteration":45,"passed_time":1.417626119,"remaining_time":29.40033299},
{"learn":[0.1642546593],"iteration":46,"passed_time":1.447475915,"remaining_time":29.34988399},
{"learn":[0.1621404373],"iteration":47,"passed_time":1.477740249,"remaining_time":29.30851494},
{"learn":[0.1604820479],"iteration":48,"passed_time":1.50739087,"remaining_time":29.25568811},
{"learn":[0.1585772718],"iteration":49,"passed_time":1.536871275,"remaining_time":29.20055423},
{"learn":[0.1563456457],"iteration":50,"passed_time":1.56812664,"remaining_time":29.17945454},
{"learn":[0.1544564833],"iteration":51,"passed_time":1.59797932,"remaining_time":29.13239221},
{"learn":[0.1519642081],"iteration":52,"passed_time":1.632188518,"remaining_time":29.16382126},
{"learn":[0.1499914655],"iteration":53,"passed_time":1.661822811,"remaining_time":29.11267369},
{"learn":[0.1482316854],"iteration":54,"passed_time":1.692283092,"remaining_time":29.0765004},
{"learn":[0.1462027851],"iteration":55,"passed_time":1.722754269,"remaining_time":29.04071483},
{"learn":[0.144810921],"iteration":56,"passed_time":1.75099453,"remaining_time":28.96820775},
{"learn":[0.1433412418],"iteration":57,"passed_time":1.782069278,"remaining_time":28.9432631},
{"learn":[0.1419515583],"iteration":58,"passed_time":1.813271738,"remaining_time":28.92014756},
{"learn":[0.1402266647],"iteration":59,"passed_time":1.843269946,"remaining_time":28.87789582},
{"learn":[0.1387395054],"iteration":60,"passed_time":1.873778501,"remaining_time":28.84390185},
{"learn":[0.1371890376],"iteration":61,"passed_time":1.906434843,"remaining_time":28.84251424},
{"learn":[0.1357373288],"iteration":62,"passed_time":1.935115819,"remaining_time":28.7810083},
{"learn":[0.1347400685],"iteration":63,"passed_time":1.963472249,"remaining_time":28.71578163},
{"learn":[0.1333196183],"iteration":64,"passed_time":1.991869529,"remaining_time":28.65227707},
{"learn":[0.1322020999],"iteration":65,"passed_time":2.019287998,"remaining_time":28.5759847},
{"learn":[0.1311521165],"iteration":66,"passed_time":2.048525832,"remaining_time":28.52648658},
{"learn":[0.1300134087],"iteration":67,"passed_time":2.078012747,"remaining_time":28.48099824},
{"learn":[0.1289842328],"iteration":68,"passed_time":2.106379742,"remaining_time":28.42086289},
{"learn":[0.1276852326],"iteration":69,"passed_time":2.13562575,"remaining_time":28.37331353},
{"learn":[0.1258889296],"iteration":70,"passed_time":2.168126548,"remaining_time":28.36886709},
{"learn":[0.1250264245],"iteration":71,"passed_time":2.198499649,"remaining_time":28.3362177},
{"learn":[0.1242069645],"iteration":72,"passed_time":2.226492216,"remaining_time":28.27340116},
{"learn":[0.1234999911],"iteration":73,"passed_time":2.255353499,"remaining_time":28.22239649},
{"learn":[0.1222017218],"iteration":74,"passed_time":2.284858465,"remaining_time":28.17992107},
{"learn":[0.1211553203],"iteration":75,"passed_time":2.31455509,"remaining_time":28.14011715},
{"learn":[0.1203069518],"iteration":76,"passed_time":2.342347999,"remaining_time":28.07775589},
{"learn":[0.1195688477],"iteration":77,"passed_time":2.371695292,"remaining_time":28.03465461},
{"learn":[0.1181395537],"iteration":78,"passed_time":2.400691948,"remaining_time":27.98781372},
{"learn":[0.1172032538],"iteration":79,"passed_time":2.429775233,"remaining_time":27.94241518},
{"learn":[0.1163181341],"iteration":80,"passed_time":2.460484446,"remaining_time":27.91586674},
{"learn":[0.1149699406],"iteration":81,"passed_time":2.491207803,"remaining_time":27.88937516},
{"learn":[0.1142201889],"iteration":82,"passed_time":2.519752907,"remaining_time":27.83871585},
{"learn":[0.1134355624],"iteration":83,"passed_time":2.550206482,"remaining_time":27.8093945},
{"learn":[0.1128020666],"iteration":84,"passed_time":2.579609583,"remaining_time":27.76873846},
{"learn":[0.1122304158],"iteration":85,"passed_time":2.615624737,"remaining_time":27.79861639},
{"learn":[0.1116407182],"iteration":86,"passed_time":2.644118016,"remaining_time":27.74804309},
{"learn":[0.1106758373],"iteration":87,"passed_time":2.674357299,"remaining_time":27.71606656},
{"learn":[0.1099011701],"iteration":88,"passed_time":2.703347786,"remaining_time":27.67134644},
{"learn":[0.1093128668],"iteration":89,"passed_time":2.731248998,"remaining_time":27.61596209},
{"learn":[0.108587519],"iteration":90,"passed_time":2.761425275,"remaining_time":27.58390742},
{"learn":[0.1076781092],"iteration":91,"passed_time":2.790647662,"remaining_time":27.5424791},
{"learn":[0.1070534264],"iteration":92,"passed_time":2.818729536,"remaining_time":27.49019021},
{"learn":[0.1064757371],"iteration":93,"passed_time":2.848476029,"remaining_time":27.45446045},
{"learn":[0.1058144939],"iteration":94,"passed_time":2.877946718,"remaining_time":27.41622926},
{"learn":[0.1050113829],"iteration":95,"passed_time":2.909148313,"remaining_time":27.39447995},
{"learn":[0.1042563665],"iteration":96,"passed_time":2.937379827,"remaining_time":27.34488644},
{"learn":[0.1035831801],"iteration":97,"passed_time":2.967350525,"remaining_time":27.31173646},
{"learn":[0.1030483986],"iteration":98,"passed_time":2.995593281,"remaining_time":27.26292471},
{"learn":[0.1026962948],"iteration":99,"passed_time":3.023780081,"remaining_time":27.21402073},
{"learn":[0.1020777872],"iteration":100,"passed_time":3.053222735,"remaining_time":27.17670533},
{"learn":[0.1015389135],"iteration":101,"passed_time":3.081195011,"remaining_time":27.12659921},
{"learn":[0.1007811515],"iteration":102,"passed_time":3.112570634,"remaining_time":27.10656174},
{"learn":[0.1002471371],"iteration":103,"passed_time":3.141705274,"remaining_time":27.06699928},
{"learn":[0.09952433685],"iteration":104,"passed_time":3.170747495,"remaining_time":27.0268477},
{"learn":[0.09895753095],"iteration":105,"passed_time":3.200818477,"remaining_time":26.99558225},
{"learn":[0.09853404878],"iteration":106,"passed_time":3.229274658,"remaining_time":26.95086233},
{"learn":[0.09791565195],"iteration":107,"passed_time":3.260233782,"remaining_time":26.92711605},
{"learn":[0.09719063206],"iteration":108,"passed_time":3.29235049,"remaining_time":26.91269987},
{"learn":[0.09640095905],"iteration":109,"passed_time":3.321155103,"remaining_time":26.87116402},
{"learn":[0.0955813542],"iteration":110,"passed_time":3.34985206,"remaining_time":26.82899533},
{"learn":[0.09500267222],"iteration":111,"passed_time":3.380618835,"remaining_time":26.80347791},
{"learn":[0.09435985237],"iteration":112,"passed_time":3.411716469,"remaining_time":26.78046467},
{"learn":[0.09381014306],"iteration":113,"passed_time":3.438908056,"remaining_time":26.72695208},
{"learn":[0.09317012021],"iteration":114,"passed_time":3.46690297,"remaining_time":26.68007938},
{"learn":[0.09253194031],"iteration":115,"passed_time":3.49612042,"remaining_time":26.64284872},
{"learn":[0.09200384382],"iteration":116,"passed_time":3.525043263,"remaining_time":26.60353163},
{"learn":[0.09164641874],"iteration":117,"passed_time":3.553639529,"remaining_time":26.5619497},
{"learn":[0.09117284483],"iteration":118,"passed_time":3.584614723,"remaining_time":26.53819807},
{"learn":[0.09074223757],"iteration":119,"passed_time":3.617057117,"remaining_time":26.52508552},
{"learn":[0.09027271926],"iteration":120,"passed_time":3.646148577,"remaining_time":26.48731074},
{"learn":[0.08974828595],"iteration":121,"passed_time":3.674954836,"remaining_time":26.44762579},
{"learn":[0.0893732492],"iteration":122,"passed_time":3.703024981,"remaining_time":26.40286917},
{"learn":[0.08880511453],"iteration":123,"passed_time":3.732241439,"remaining_time":26.36647985},
{"learn":[0.0884635883],"iteration":124,"passed_time":3.760888906,"remaining_time":26.32622234},
{"learn":[0.08803969241],"iteration":125,"passed_time":3.790179534,"remaining_time":26.29061042},
{"learn":[0.08749191248],"iteration":126,"passed_time":3.820537976,"remaining_time":26.26243821},
{"learn":[0.08696400399],"iteration":127,"passed_time":3.851771476,"remaining_time":26.24019318},
{"learn":[0.08633051887],"iteration":128,"passed_time":3.880017794,"remaining_time":26.19763952},
{"learn":[0.08602570598],"iteration":129,"passed_time":3.912015755,"remaining_time":26.18041313},
{"learn":[0.08539392169],"iteration":130,"passed_time":3.942465675,"remaining_time":26.15269215},
{"learn":[0.08504586805],"iteration":131,"passed_time":3.969858379,"remaining_time":26.10482631},
{"learn":[0.08466437297],"iteration":132,"passed_time":3.999850548,"remaining_time":26.07421372},
{"learn":[0.0843088071],"iteration":133,"passed_time":4.027705376,"remaining_time":26.02979743},
{"learn":[0.08389493552],"iteration":134,"passed_time":4.056819406,"remaining_time":25.99369471},
{"learn":[0.0835259852],"iteration":135,"passed_time":4.086998814,"remaining_time":25.96446306},
{"learn":[0.08310628272],"iteration":136,"passed_time":4.11786508,"remaining_time":25.93954426},
{"learn":[0.08274077904],"iteration":137,"passed_time":4.149164496,"remaining_time":25.91724489},
{"learn":[0.08225203367],"iteration":138,"passed_time":4.179467837,"remaining_time":25.8886461},
{"learn":[0.08185642145],"iteration":139,"passed_time":4.208769726,"remaining_time":25.85387117},
{"learn":[0.08144570843],"iteration":140,"passed_time":4.238023664,"remaining_time":25.81888175},
{"learn":[0.08124429105],"iteration":141,"passed_time":4.26382866,"remaining_time":25.76313374},
{"learn":[0.08089486766],"iteration":142,"passed_time":4.292338699,"remaining_time":25.72401584},
{"learn":[0.08048455712],"iteration":143,"passed_time":4.322471415,"remaining_time":25.69469119},
{"learn":[0.08009857554],"iteration":144,"passed_time":4.351807112,"remaining_time":25.66065573},
{"learn":[0.07978503397],"iteration":145,"passed_time":4.380656476,"remaining_time":25.62383994},
{"learn":[0.07947215329],"iteration":146,"passed_time":4.410656367,"remaining_time":25.59380872},
{"learn":[0.07914512443],"iteration":147,"passed_time":4.438611124,"remaining_time":25.55200458},
{"learn":[0.07858956058],"iteration":148,"passed_time":4.470178035,"remaining_time":25.53101683},
{"learn":[0.07829024265],"iteration":149,"passed_time":4.498702493,"remaining_time":25.49264746},
{"learn":[0.07792952431],"iteration":150,"passed_time":4.526896725,"remaining_time":25.45255179},
{"learn":[0.07760452116],"iteration":151,"passed_time":4.556157663,"remaining_time":25.41856381},
{"learn":[0.07728993472],"iteration":152,"passed_time":4.591918125,"remaining_time":25.42061864},
{"learn":[0.07696456184],"iteration":153,"passed_time":4.621310678,"remaining_time":25.38720022},
{"learn":[0.07651271011],"iteration":154,"passed_time":4.649161089,"remaining_time":25.34542658},
{"learn":[0.07610813387],"iteration":155,"passed_time":4.679504357,"remaining_time":25.31731844},
{"learn":[0.07576532778],"iteration":156,"passed_time":4.707581063,"remaining_time":25.2770117},
{"learn":[0.07542519695],"iteration":157,"passed_time":4.73760338,"remaining_time":25.24722814},
{"learn":[0.07492392893],"iteration":158,"passed_time":4.767622021,"remaining_time":25.21742214},
{"learn":[0.07456252514],"iteration":159,"passed_time":4.796941623,"remaining_time":25.18394352},
{"learn":[0.07406322127],"iteration":160,"passed_time":4.826299845,"remaining_time":25.15071783},
{"learn":[0.07379390131],"iteration":161,"passed_time":4.854108584,"remaining_time":25.10952465},
{"learn":[0.07340727466],"iteration":162,"passed_time":4.882847749,"remaining_time":25.07327341},
{"learn":[0.07316562606],"iteration":163,"passed_time":4.912315279,"remaining_time":25.04082667},
{"learn":[0.07280235164],"iteration":164,"passed_time":4.944055102,"remaining_time":25.01991521},
{"learn":[0.07241188086],"iteration":165,"passed_time":4.973633181,"remaining_time":24.98801249},
{"learn":[0.07214287955],"iteration":166,"passed_time":5.000868293,"remaining_time":24.94445083},
{"learn":[0.07186392704],"iteration":167,"passed_time":5.029024336,"remaining_time":24.90564433},
{"learn":[0.07163475982],"iteration":168,"passed_time":5.057296977,"remaining_time":24.86753721},
{"learn":[0.07134855767],"iteration":169,"passed_time":5.086697634,"remaining_time":24.83505316},
{"learn":[0.07108920126],"iteration":170,"passed_time":5.113771962,"remaining_time":24.79132723},
{"learn":[0.07087738037],"iteration":171,"passed_time":5.142909972,"remaining_time":24.7577294},
{"learn":[0.07063260368],"iteration":172,"passed_time":5.173505742,"remaining_time":24.73115173},
{"learn":[0.07018945246],"iteration":173,"passed_time":5.2035171,"remaining_time":24.70175359},
{"learn":[0.06995853492],"iteration":174,"passed_time":5.232530001,"remaining_time":24.66764143},
{"learn":[0.06959469097],"iteration":175,"passed_time":5.260929692,"remaining_time":24.63071628},
{"learn":[0.0693581776],"iteration":176,"passed_time":5.28827856,"remaining_time":24.58900144},
{"learn":[0.0690286694],"iteration":177,"passed_time":5.319499677,"remaining_time":24.56532997},
{"learn":[0.06877043413],"iteration":178,"passed_time":5.347871721,"remaining_time":24.52850661},
{"learn":[0.06846797928],"iteration":179,"passed_time":5.375542842,"remaining_time":24.48858406},
{"learn":[0.06822027426],"iteration":180,"passed_time":5.407557937,"remaining_time":24.46845277},
{"learn":[0.06769309958],"iteration":181,"passed_time":5.441338235,"remaining_time":24.4561246},
{"learn":[0.06733371142],"iteration":182,"passed_time":5.469705576,"remaining_time":24.41939593},
{"learn":[0.06702484954],"iteration":183,"passed_time":5.498325038,"remaining_time":24.38387625},
{"learn":[0.06673782852],"iteration":184,"passed_time":5.528776469,"remaining_time":24.35650174},
{"learn":[0.0663957664],"iteration":185,"passed_time":5.556946312,"remaining_time":24.31910913},
{"learn":[0.06614644374],"iteration":186,"passed_time":5.591459052,"remaining_time":24.30939149},
{"learn":[0.0659533664],"iteration":187,"passed_time":5.620100134,"remaining_time":24.27404952},
{"learn":[0.06568750041],"iteration":188,"passed_time":5.648660371,"remaining_time":24.23843154},
{"learn":[0.06549034532],"iteration":189,"passed_time":5.677963238,"remaining_time":24.20605381},
{"learn":[0.06526392472],"iteration":190,"passed_time":5.707395776,"remaining_time":24.1742575},
{"learn":[0.0649931596],"iteration":191,"passed_time":5.734481784,"remaining_time":24.13261084},
{"learn":[0.06478687361],"iteration":192,"passed_time":5.762552383,"remaining_time":24.09523198},
{"learn":[0.06462357142],"iteration":193,"passed_time":5.790256737,"remaining_time":24.05642748},
{"learn":[0.06445561691],"iteration":194,"passed_time":5.818529159,"remaining_time":24.02008191},
{"learn":[0.06423885823],"iteration":195,"passed_time":5.852351224,"remaining_time":24.00658359},
{"learn":[0.06400126389],"iteration":196,"passed_time":5.881425015,"remaining_time":23.9735243},
{"learn":[0.06383833929],"iteration":197,"passed_time":5.909152455,"remaining_time":23.93505186},
{"learn":[0.06366722819],"iteration":198,"passed_time":5.93767146,"remaining_time":23.89987356},
{"learn":[0.06338382221],"iteration":199,"passed_time":5.968222043,"remaining_time":23.87288817},
{"learn":[0.06315250967],"iteration":200,"passed_time":5.997361039,"remaining_time":23.84025607},
{"learn":[0.06275839845],"iteration":201,"passed_time":6.02704409,"remaining_time":23.80980784},
{"learn":[0.0624735651],"iteration":202,"passed_time":6.056585476,"remaining_time":23.77881096},
{"learn":[0.06228655584],"iteration":203,"passed_time":6.085079003,"remaining_time":23.74373964},
{"learn":[0.06205007172],"iteration":204,"passed_time":6.114735157,"remaining_time":23.71324122},
{"learn":[0.06183105359],"iteration":205,"passed_time":6.143847006,"remaining_time":23.68065302},
{"learn":[0.06163461519],"iteration":206,"passed_time":6.171774532,"remaining_time":23.64356137},
{"learn":[0.06136134829],"iteration":207,"passed_time":6.19892036,"remaining_time":23.60358137},
{"learn":[0.06109090526],"iteration":208,"passed_time":6.229247833,"remaining_time":23.57576572},
{"learn":[0.06091440168],"iteration":209,"passed_time":6.257726837,"remaining_time":23.54097239},
{"learn":[0.06071902853],"iteration":210,"passed_time":6.286155653,"remaining_time":23.50605123},
{"learn":[0.06049718316],"iteration":211,"passed_time":6.314992947,"remaining_time":23.47270963},
{"learn":[0.06015020973],"iteration":212,"passed_time":6.344429352,"remaining_time":23.44162394},
{"learn":[0.05991915741],"iteration":213,"passed_time":6.373229757,"remaining_time":23.4082177},
{"learn":[0.05966561818],"iteration":214,"passed_time":6.403607923,"remaining_time":23.38061497},
{"learn":[0.05940321542],"iteration":215,"passed_time":6.43196976,"remaining_time":23.34566802},
{"learn":[0.05917277424],"iteration":216,"passed_time":6.461802834,"remaining_time":23.31609041},
{"learn":[0.05888442877],"iteration":217,"passed_time":6.492227852,"remaining_time":23.28863385},
{"learn":[0.05876432605],"iteration":218,"passed_time":6.520136377,"remaining_time":23.25217585},
{"learn":[0.05855961184],"iteration":219,"passed_time":6.551132446,"remaining_time":23.22674231},
{"learn":[0.05842949918],"iteration":220,"passed_time":6.582978892,"remaining_time":23.20425591},
{"learn":[0.05817612325],"iteration":221,"passed_time":6.611208655,"remaining_time":23.16901051},
{"learn":[0.05797461983],"iteration":222,"passed_time":6.640972907,"remaining_time":23.13917466},
{"learn":[0.0577202638],"iteration":223,"passed_time":6.668887484,"remaining_time":23.10293164},
{"learn":[0.05747691675],"iteration":224,"passed_time":6.697273785,"remaining_time":23.06838748},
{"learn":[0.05723277002],"iteration":225,"passed_time":6.727377281,"remaining_time":23.03977883},
{"learn":[0.05704499521],"iteration":226,"passed_time":6.755060575,"remaining_time":23.00291552},
{"learn":[0.05676010294],"iteration":227,"passed_time":6.786067768,"remaining_time":22.97738735},
{"learn":[0.05646751695],"iteration":228,"passed_time":6.8150678,"remaining_time":22.9450536},
{"learn":[0.05630967067],"iteration":229,"passed_time":6.84391839,"remaining_time":22.91224852},
{"learn":[0.05611513251],"iteration":230,"passed_time":6.873817487,"remaining_time":22.88296817},
{"learn":[0.055911066],"iteration":231,"passed_time":6.902699822,"remaining_time":22.85031665},
{"learn":[0.05562321349],"iteration":232,"passed_time":6.931934111,"remaining_time":22.81885606},
{"learn":[0.05539478091],"iteration":233,"passed_time":6.961530662,"remaining_time":22.78860037},
{"learn":[0.05519997949],"iteration":234,"passed_time":6.991692183,"remaining_time":22.76018945},
{"learn":[0.05501544555],"iteration":235,"passed_time":7.020507197,"remaining_time":22.72740465},
{"learn":[0.05483316267],"iteration":236,"passed_time":7.049275212,"remaining_time":22.69450205},
{"learn":[0.05459931677],"iteration":237,"passed_time":7.078133071,"remaining_time":22.66192185},
{"learn":[0.05444451135],"iteration":238,"passed_time":7.105640734,"remaining_time":22.62507363},
{"learn":[0.05436705805],"iteration":239,"passed_time":7.132145682,"remaining_time":22.58512799},
{"learn":[0.05417280936],"iteration":240,"passed_time":7.160554792,"remaining_time":22.55129082},
{"learn":[0.05397671077],"iteration":241,"passed_time":7.189514894,"remaining_time":22.51922434},
{"learn":[0.05365044039],"iteration":242,"passed_time":7.220503898,"remaining_time":22.49350391},
{"learn":[0.05350806508],"iteration":243,"passed_time":7.247896371,"remaining_time":22.45659695},
{"learn":[0.05330894043],"iteration":244,"passed_time":7.276545617,"remaining_time":22.42364057},
{"learn":[0.05309193988],"iteration":245,"passed_time":7.304299548,"remaining_time":22.38797504},
{"learn":[0.0529971989],"iteration":246,"passed_time":7.331510403,"remaining_time":22.35071795},
{"learn":[0.05284126204],"iteration":247,"passed_time":7.358993466,"remaining_time":22.31436728},
{"learn":[0.05269739527],"iteration":248,"passed_time":7.38709236,"remaining_time":22.27994523},
{"learn":[0.05245093559],"iteration":249,"passed_time":7.419756916,"remaining_time":22.25927075},
{"learn":[0.0521757265],"iteration":250,"passed_time":7.448720644,"remaining_time":22.22745722},
{"learn":[0.05193282953],"iteration":251,"passed_time":7.477298955,"remaining_time":22.1945223},
{"learn":[0.05170817657],"iteration":252,"passed_time":7.508379234,"remaining_time":22.16900904},
{"learn":[0.0515444554],"iteration":253,"passed_time":7.536061754,"remaining_time":22.13347271},
{"learn":[0.05127309019],"iteration":254,"passed_time":7.569342309,"remaining_time":22.11435302},
{"learn":[0.05108387993],"iteration":255,"passed_time":7.599631523,"remaining_time":22.08642911},
{"learn":[0.05085155399],"iteration":256,"passed_time":7.628567261,"remaining_time":22.05457383},
{"learn":[0.05068313473],"iteration":257,"passed_time":7.65570839,"remaining_time":22.01757994},
{"learn":[0.05054630639],"iteration":258,"passed_time":7.684917948,"remaining_time":21.98657992},
{"learn":[0.05034587567],"iteration":259,"passed_time":7.713507584,"remaining_time":21.95382928},
{"learn":[0.05016094955],"iteration":260,"passed_time":7.740901479,"remaining_time":21.91772488},
{"learn":[0.04989315629],"iteration":261,"passed_time":7.774367219,"remaining_time":21.89879011},
{"learn":[0.04972606292],"iteration":262,"passed_time":7.801550306,"remaining_time":21.86213907},
{"learn":[0.04951225939],"iteration":263,"passed_time":7.831317071,"remaining_time":21.83276274},
{"learn":[0.04928692308],"iteration":264,"passed_time":7.863126519,"remaining_time":21.80904903},
{"learn":[0.04915766471],"iteration":265,"passed_time":7.891169145,"remaining_time":21.77488027},
{"learn":[0.04894893715],"iteration":266,"passed_time":7.919975008,"remaining_time":21.74285274},
{"learn":[0.04886425095],"iteration":267,"passed_time":7.946656827,"remaining_time":21.70504775},
{"learn":[0.04871787114],"iteration":268,"passed_time":7.976164651,"remaining_time":21.67500506},
{"learn":[0.04856095609],"iteration":269,"passed_time":8.007776866,"remaining_time":21.65065597},
{"learn":[0.04842881878],"iteration":270,"passed_time":8.036097132,"remaining_time":21.61739782},
{"learn":[0.04822056759],"iteration":271,"passed_time":8.066912429,"remaining_time":21.59085385},
{"learn":[0.04807640022],"iteration":272,"passed_time":8.095179972,"remaining_time":21.55749392},
{"learn":[0.047870567],"iteration":273,"passed_time":8.125459606,"remaining_time":21.52950246},
{"learn":[0.04764443927],"iteration":274,"passed_time":8.154810456,"remaining_time":21.49904575},
{"learn":[0.04754480067],"iteration":275,"passed_time":8.182805838,"remaining_time":21.4650414},
{"learn":[0.04740271493],"iteration":276,"passed_time":8.211575033,"remaining_time":21.43310018},
{"learn":[0.04727063149],"iteration":277,"passed_time":8.239644547,"remaining_time":21.39936462},
{"learn":[0.04715857711],"iteration":278,"passed_time":8.269653924,"remaining_time":21.37068272},
{"learn":[0.0469163455],"iteration":279,"passed_time":8.302203847,"remaining_time":21.34852418},
{"learn":[0.04671883812],"iteration":280,"passed_time":8.329472323,"remaining_time":21.31277794},
{"learn":[0.04654299326],"iteration":281,"passed_time":8.358318201,"remaining_time":21.28110804},
{"learn":[0.04641273596],"iteration":282,"passed_time":8.388769128,"remaining_time":21.25352461},
{"learn":[0.04620370835],"iteration":283,"passed_time":8.417217038,"remaining_time":21.22087112},
{"learn":[0.04612534694],"iteration":284,"passed_time":8.444698199,"remaining_time":21.1858218},
{"learn":[0.0459482053],"iteration":285,"passed_time":8.481460917,"remaining_time":21.17399683},
{"learn":[0.04582742851],"iteration":286,"passed_time":8.518716882,"remaining_time":21.16322347},
{"learn":[0.04573078306],"iteration":287,"passed_time":8.554680532,"remaining_time":21.14907131},
{"learn":[0.04554178035],"iteration":288,"passed_time":8.591846098,"remaining_time":21.13772518},
{"learn":[0.04537505606],"iteration":289,"passed_time":8.620408107,"remaining_time":21.10513709},
{"learn":[0.04525938678],"iteration":290,"passed_time":8.647514145,"remaining_time":21.06902931},
{"learn":[0.04500480264],"iteration":291,"passed_time":8.676485281,"remaining_time":21.03750541},
{"learn":[0.04485048129],"iteration":292,"passed_time":8.705556432,"remaining_time":21.00624026},
{"learn":[0.04456411725],"iteration":293,"passed_time":8.734311963,"remaining_time":20.97423213},
{"learn":[0.04437592677],"iteration":294,"passed_time":8.76606698,"remaining_time":20.94941431},
{"learn":[0.0442151304],"iteration":295,"passed_time":8.794672073,"remaining_time":20.9170579},
{"learn":[0.04400396151],"iteration":296,"passed_time":8.823800527,"remaining_time":20.88596556},
{"learn":[0.04393433791],"iteration":297,"passed_time":8.850374703,"remaining_time":20.84886927},
{"learn":[0.04381761912],"iteration":298,"passed_time":8.878253825,"remaining_time":20.81490278},
{"learn":[0.04366482826],"iteration":299,"passed_time":8.910227495,"remaining_time":20.79053082},
{"learn":[0.04345454472],"iteration":300,"passed_time":8.944150179,"remaining_time":20.77063447},
{"learn":[0.04330306804],"iteration":301,"passed_time":8.97235445,"remaining_time":20.7374285},
{"learn":[0.04321657947],"iteration":302,"passed_time":9.001268658,"remaining_time":20.70588863},
{"learn":[0.04314521564],"iteration":303,"passed_time":9.029642713,"remaining_time":20.67312937},
{"learn":[0.04299647882],"iteration":304,"passed_time":9.0582642,"remaining_time":20.64096269},
{"learn":[0.0428083319],"iteration":305,"passed_time":9.089473991,"remaining_time":20.61468938},
{"learn":[0.04269331288],"iteration":306,"passed_time":9.118468474,"remaining_time":20.58338323},
{"learn":[0.0425759635],"iteration":307,"passed_time":9.146922557,"remaining_time":20.55087795},
{"learn":[0.04241258279],"iteration":308,"passed_time":9.175192304,"remaining_time":20.51798667},
{"learn":[0.04228497445],"iteration":309,"passed_time":9.202837296,"remaining_time":20.48373463},
{"learn":[0.04213162095],"iteration":310,"passed_time":9.23091739,"remaining_time":20.45048901},
{"learn":[0.04201080829],"iteration":311,"passed_time":9.259466993,"remaining_time":20.41831183},
{"learn":[0.04187238864],"iteration":312,"passed_time":9.28709012,"remaining_time":20.38412432},
{"learn":[0.04172839814],"iteration":313,"passed_time":9.316122535,"remaining_time":20.35305751},
{"learn":[0.04162313542],"iteration":314,"passed_time":9.346150868,"remaining_time":20.32416935},
{"learn":[0.04153575742],"iteration":315,"passed_time":9.374510778,"remaining_time":20.29166257},
{"learn":[0.04142401342],"iteration":316,"passed_time":9.402259628,"remaining_time":20.25786538},
{"learn":[0.04127601278],"iteration":317,"passed_time":9.430916033,"remaining_time":20.22605262},
{"learn":[0.04109649232],"iteration":318,"passed_time":9.459097827,"remaining_time":20.19324646},
{"learn":[0.04103494908],"iteration":319,"passed_time":9.486462123,"remaining_time":20.15873201},
{"learn":[0.04089063748],"iteration":320,"passed_time":9.515032981,"remaining_time":20.12681431},
{"learn":[0.04071743845],"iteration":321,"passed_time":9.544349807,"remaining_time":20.0964881},
{"learn":[0.04057495986],"iteration":322,"passed_time":9.576602917,"remaining_time":20.07232252},
{"learn":[0.04049050667],"iteration":323,"passed_time":9.604971414,"remaining_time":20.04000209},
{"learn":[0.04033945482],"iteration":324,"passed_time":9.633523431,"remaining_time":20.00808713},
{"learn":[0.04022074016],"iteration":325,"passed_time":9.661293775,"remaining_time":19.9745767},
{"learn":[0.04011291037],"iteration":326,"passed_time":9.688252395,"remaining_time":19.93943077},
{"learn":[0.04003723665],"iteration":327,"passed_time":9.715710463,"remaining_time":19.90535802},
{"learn":[0.03987115958],"iteration":328,"passed_time":9.746461282,"remaining_time":19.8780411},
{"learn":[0.03973037879],"iteration":329,"passed_time":9.775285466,"remaining_time":19.8467917},
{"learn":[0.03957497142],"iteration":330,"passed_time":9.803313531,"remaining_time":19.81394789},
{"learn":[0.03943208862],"iteration":331,"passed_time":9.830762169,"remaining_time":19.77996726},
{"learn":[0.03930885505],"iteration":332,"passed_time":9.857971706,"remaining_time":19.74554693},
{"learn":[0.03918924513],"iteration":333,"passed_time":9.887797446,"remaining_time":19.71638652},
{"learn":[0.03910202376],"iteration":334,"passed_time":9.914693973,"remaining_time":19.68140744},
{"learn":[0.03894271731],"iteration":335,"passed_time":9.94618337,"remaining_time":19.65555285},
{"learn":[0.03883393492],"iteration":336,"passed_time":9.972842634,"remaining_time":19.62016221},
{"learn":[0.03872117802],"iteration":337,"passed_time":10.0005162,"remaining_time":19.58680985},
{"learn":[0.03858396744],"iteration":338,"passed_time":10.02953556,"remaining_time":19.55611506},
{"learn":[0.03846047805],"iteration":339,"passed_time":10.06235174,"remaining_time":19.53280043},
{"learn":[0.03834770673],"iteration":340,"passed_time":10.09169525,"remaining_time":19.50271897},
{"learn":[0.03826193344],"iteration":341,"passed_time":10.11888965,"remaining_time":19.46850698},
{"learn":[0.03807889697],"iteration":342,"passed_time":10.14777317,"remaining_time":19.43757134},
{"learn":[0.03798634556],"iteration":343,"passed_time":10.17557034,"remaining_time":19.40457599},
{"learn":[0.03782116791],"iteration":344,"passed_time":10.2075765,"remaining_time":19.37960176},
{"learn":[0.03768471075],"iteration":345,"passed_time":10.23604817,"remaining_time":19.34790608},
{"learn":[0.03763600535],"iteration":346,"passed_time":10.26324462,"remaining_time":19.31382922},
{"learn":[0.03747767584],"iteration":347,"passed_time":10.29180635,"remaining_time":19.28234983},
{"learn":[0.03736518141],"iteration":348,"passed_time":10.32218998,"remaining_time":19.2542856},
{"learn":[0.03726525947],"iteration":349,"passed_time":10.35005395,"remaining_time":19.22152877},
{"learn":[0.03716830844],"iteration":350,"passed_time":10.37688269,"remaining_time":19.18688565},
{"learn":[0.03710006358],"iteration":351,"passed_time":10.40477839,"remaining_time":19.15425112},
{"learn":[0.03694084789],"iteration":352,"passed_time":10.43596352,"remaining_time":19.12767252},
{"learn":[0.03687986415],"iteration":353,"passed_time":10.46388319,"remaining_time":19.09510888},
{"learn":[0.03682339356],"iteration":354,"passed_time":10.49172067,"remaining_time":19.06242206},
{"learn":[0.0367161867],"iteration":355,"passed_time":10.52045423,"remaining_time":19.0313835},
{"learn":[0.03659741957],"iteration":356,"passed_time":10.55016558,"remaining_time":19.00211896},
{"learn":[0.0365005363],"iteration":357,"passed_time":10.58211649,"remaining_time":18.97686812},
{"learn":[0.03637467173],"iteration":358,"passed_time":10.61205393,"remaining_time":18.94798487},
{"learn":[0.03629709231],"iteration":359,"passed_time":10.63909715,"remaining_time":18.91395048},
{"learn":[0.03625780577],"iteration":360,"passed_time":10.66593958,"remaining_time":18.87959942},
{"learn":[0.0362067618],"iteration":361,"passed_time":10.69410035,"remaining_time":18.84761333},
{"learn":[0.03608713729],"iteration":362,"passed_time":10.72276161,"remaining_time":18.81652657},
{"learn":[0.03598103669],"iteration":363,"passed_time":10.75296051,"remaining_time":18.78813979},
{"learn":[0.03582524457],"iteration":364,"passed_time":10.78343653,"remaining_time":18.7602252},
{"learn":[0.03575529092],"iteration":365,"passed_time":10.81199276,"remaining_time":18.72897107},
{"learn":[0.03560926545],"iteration":366,"passed_time":10.84390253,"remaining_time":18.70351581},
{"learn":[0.03547391852],"iteration":367,"passed_time":10.87401511,"remaining_time":18.674939},
{"learn":[0.03541425497],"iteration":368,"passed_time":10.90212112,"remaining_time":18.64292257},
{"learn":[0.03533653308],"iteration":369,"passed_time":10.93057535,"remaining_time":18.61152019},
{"learn":[0.03519925671],"iteration":370,"passed_time":10.95999215,"remaining_time":18.58176566},
{"learn":[0.03510013251],"iteration":371,"passed_time":10.98898336,"remaining_time":18.55129449},
{"learn":[0.03497329471],"iteration":372,"passed_time":11.01783434,"remaining_time":18.52059553},
{"learn":[0.03486899851],"iteration":373,"passed_time":11.04562937,"remaining_time":18.488139},
{"learn":[0.03476556166],"iteration":374,"passed_time":11.07541759,"remaining_time":18.45902932},
{"learn":[0.03469404434],"iteration":375,"passed_time":11.10362948,"remaining_time":18.42729999},
{"learn":[0.03464222186],"iteration":376,"passed_time":11.13186838,"remaining_time":18.39563395},
{"learn":[0.03457149517],"iteration":377,"passed_time":11.16507375,"remaining_time":18.37215839},
{"learn":[0.03450475097],"iteration":378,"passed_time":11.19309487,"remaining_time":18.34013697},
{"learn":[0.03441849633],"iteration":379,"passed_time":11.2206386,"remaining_time":18.30735771},
{"learn":[0.03429303476],"iteration":380,"passed_time":11.25114027,"remaining_time":18.27941162},
{"learn":[0.03419194555],"iteration":381,"passed_time":11.28152414,"remaining_time":18.25126156},
{"learn":[0.03413705218],"iteration":382,"passed_time":11.30959559,"remaining_time":18.21937461},
{"learn":[0.03399851096],"iteration":383,"passed_time":11.33915339,"remaining_time":18.18989189},
{"learn":[0.03391307497],"iteration":384,"passed_time":11.36543251,"remaining_time":18.1551714},
{"learn":[0.03384760503],"iteration":385,"passed_time":11.3930122,"remaining_time":18.12256344},
{"learn":[0.03376458827],"iteration":386,"passed_time":11.4208977,"remaining_time":18.09046586},
{"learn":[0.03369648929],"iteration":387,"passed_time":11.44760363,"remaining_time":18.05652944},
{"learn":[0.03363142961],"iteration":388,"passed_time":11.47407316,"remaining_time":18.02225886},
{"learn":[0.03351711153],"iteration":389,"passed_time":11.50610199,"remaining_time":17.99672362},
{"learn":[0.03339198907],"iteration":390,"passed_time":11.53404933,"remaining_time":17.96479806},
{"learn":[0.0333153104],"iteration":391,"passed_time":11.56260208,"remaining_time":17.9338318},
{"learn":[0.03325174143],"iteration":392,"passed_time":11.5973994,"remaining_time":17.91252274},
{"learn":[0.03314816992],"iteration":393,"passed_time":11.62732806,"remaining_time":17.88365687},
{"learn":[0.03307610104],"iteration":394,"passed_time":11.65546125,"remaining_time":17.85203559},
{"learn":[0.03300307997],"iteration":395,"passed_time":11.6835318,"remaining_time":17.82033638},
{"learn":[0.03291730288],"iteration":396,"passed_time":11.71060029,"remaining_time":17.78713343},
{"learn":[0.03286321443],"iteration":397,"passed_time":11.73760274,"remaining_time":17.75386143},
{"learn":[0.03280992512],"iteration":398,"passed_time":11.76594211,"remaining_time":17.7226346},
{"learn":[0.03270514184],"iteration":399,"passed_time":11.79516866,"remaining_time":17.692753},
{"learn":[0.03263164691],"iteration":400,"passed_time":11.82179524,"remaining_time":17.65899089},
{"learn":[0.03262342211],"iteration":401,"passed_time":11.84854791,"remaining_time":17.62545186},
{"learn":[0.03255045846],"iteration":402,"passed_time":11.87754447,"remaining_time":17.5952706},
{"learn":[0.03250096164],"iteration":403,"passed_time":11.9063789,"remaining_time":17.564856},
{"learn":[0.03242433544],"iteration":404,"passed_time":11.93519357,"remaining_time":17.53442019},
{"learn":[0.03228218313],"iteration":405,"passed_time":11.96416226,"remaining_time":17.50421769},
{"learn":[0.03221490318],"iteration":406,"passed_time":11.99197963,"remaining_time":17.47234379},
{"learn":[0.03211322776],"iteration":407,"passed_time":12.02101473,"remaining_time":17.44225666},
{"learn":[0.03207241715],"iteration":408,"passed_time":12.04912279,"remaining_time":17.41083513},
{"learn":[0.03197236839],"iteration":409,"passed_time":12.07757419,"remaining_time":17.37992383},
{"learn":[0.03185137602],"iteration":410,"passed_time":12.10849554,"remaining_time":17.35256417},
{"learn":[0.03178840901],"iteration":411,"passed_time":12.13484701,"remaining_time":17.31866515},
{"learn":[0.03168000114],"iteration":412,"passed_time":12.16487214,"remaining_time":17.29002408},
{"learn":[0.03161869744],"iteration":413,"passed_time":12.19269649,"remaining_time":17.25826121},
{"learn":[0.03155884867],"iteration":414,"passed_time":12.22081578,"remaining_time":17.22693309},
{"learn":[0.03148278845],"iteration":415,"passed_time":12.2497988,"remaining_time":17.19683294},
{"learn":[0.0314311671],"iteration":416,"passed_time":12.27878721,"remaining_time":17.16674566},
{"learn":[0.03138126609],"iteration":417,"passed_time":12.30633987,"remaining_time":17.1346646},
{"learn":[0.0312462848],"iteration":418,"passed_time":12.3358698,"remaining_time":17.10534691},
{"learn":[0.03115633516],"iteration":419,"passed_time":12.36630218,"remaining_time":17.07727444},
{"learn":[0.03111378133],"iteration":420,"passed_time":12.39383271,"remaining_time":17.04519985},
{"learn":[0.03104455832],"iteration":421,"passed_time":12.42209279,"remaining_time":17.01414605},
{"learn":[0.03094430941],"iteration":422,"passed_time":12.45181912,"remaining_time":16.98510552},
{"learn":[0.0309071762],"iteration":423,"passed_time":12.47940518,"remaining_time":16.95315421},
{"learn":[0.03087596532],"iteration":424,"passed_time":12.50601193,"remaining_time":16.91989849},
{"learn":[0.03080505082],"iteration":425,"passed_time":12.53524852,"remaining_time":16.8902175},
{"learn":[0.03070278217],"iteration":426,"passed_time":12.56456441,"remaining_time":16.86064498},
{"learn":[0.0306329578],"iteration":427,"passed_time":12.60024244,"remaining_time":16.83957635},
{"learn":[0.03049702071],"iteration":428,"passed_time":12.63277407,"remaining_time":16.81425174},
{"learn":[0.03042075725],"iteration":429,"passed_time":12.66255885,"remaining_time":16.78525243},
{"learn":[0.03031847959],"iteration":430,"passed_time":12.6905665,"remaining_time":16.75390334},
{"learn":[0.03025581322],"iteration":431,"passed_time":12.71895676,"remaining_time":16.72307277},
{"learn":[0.03018076176],"iteration":432,"passed_time":12.74846391,"remaining_time":16.69371602},
{"learn":[0.03013085329],"iteration":433,"passed_time":12.77645811,"remaining_time":16.66238546},
{"learn":[0.03011926648],"iteration":434,"passed_time":12.80293353,"remaining_time":16.62909757},
{"learn":[0.0299860922],"iteration":435,"passed_time":12.8338356,"remaining_time":16.60156715},
{"learn":[0.02989701732],"iteration":436,"passed_time":12.86234784,"remaining_time":16.57094242},
{"learn":[0.02984719983],"iteration":437,"passed_time":12.88853498,"remaining_time":16.53734396},
{"learn":[0.0297605409],"iteration":438,"passed_time":12.91832919,"remaining_time":16.50838878},
{"learn":[0.02974093506],"iteration":439,"passed_time":12.94465912,"remaining_time":16.47502069},
{"learn":[0.02969410091],"iteration":440,"passed_time":12.97237335,"remaining_time":16.44343924},
{"learn":[0.0296354829],"iteration":441,"passed_time":12.99896344,"remaining_time":16.4104561},
{"learn":[0.02955871493],"iteration":442,"passed_time":13.02634961,"remaining_time":16.37850278},
{"learn":[0.02949774749],"iteration":443,"passed_time":13.05397057,"remaining_time":16.34686405},
{"learn":[0.02943583844],"iteration":444,"passed_time":13.08148603,"remaining_time":16.3151118},
{"learn":[0.02934303838],"iteration":445,"passed_time":13.11317724,"remaining_time":16.28856545},
{"learn":[0.02924987999],"iteration":446,"passed_time":13.14302172,"remaining_time":16.25971143},
{"learn":[0.02920351395],"iteration":447,"passed_time":13.17032964,"remaining_time":16.2277276},
{"learn":[0.02912196228],"iteration":448,"passed_time":13.19964035,"remaining_time":16.19822234},
{"learn":[0.02911167744],"iteration":449,"passed_time":13.22554371,"remaining_time":16.16455343},
{"learn":[0.0290854434],"iteration":450,"passed_time":13.25284736,"remaining_time":16.13262351},
{"learn":[0.02903514738],"iteration":451,"passed_time":13.27971729,"remaining_time":16.10018822},
{"learn":[0.02899371371],"iteration":452,"passed_time":13.30691856,"remaining_time":16.0681776},
{"learn":[0.02890191949],"iteration":453,"passed_time":13.3355485,"remaining_time":16.03790634},
{"learn":[0.02886529191],"iteration":454,"passed_time":13.36307936,"remaining_time":16.00632583},
{"learn":[0.02875155432],"iteration":455,"passed_time":13.39226037,"remaining_time":15.97673167},
{"learn":[0.02865503181],"iteration":456,"passed_time":13.42141736,"remaining_time":15.94711078},
{"learn":[0.02857635783],"iteration":457,"passed_time":13.45142744,"remaining_time":15.91850146},
{"learn":[0.02851712273],"iteration":458,"passed_time":13.47991919,"remaining_time":15.88809647},
{"learn":[0.02841707221],"iteration":459,"passed_time":13.50844343,"remaining_time":15.85773794},
{"learn":[0.0283630879],"iteration":460,"passed_time":13.5354576,"remaining_time":15.8256218},
{"learn":[0.02835161513],"iteration":461,"passed_time":13.56125426,"remaining_time":15.79210994},
{"learn":[0.02831563316],"iteration":462,"passed_time":13.5934334,"remaining_time":15.76603398},
{"learn":[0.02827176698],"iteration":463,"passed_time":13.62125181,"remaining_time":15.73489433},
{"learn":[0.02821295201],"iteration":464,"passed_time":13.65432604,"remaining_time":15.70981598},
{"learn":[0.02818544957],"iteration":465,"passed_time":13.68270157,"remaining_time":15.67931897},
{"learn":[0.02812481418],"iteration":466,"passed_time":13.71170035,"remaining_time":15.64954237},
{"learn":[0.02803343808],"iteration":467,"passed_time":13.74053392,"remaining_time":15.61958129},
{"learn":[0.02799550024],"iteration":468,"passed_time":13.76708468,"remaining_time":15.58704043},
{"learn":[0.02792344297],"iteration":469,"passed_time":13.7960989,"remaining_time":15.55730302},
{"learn":[0.02782944527],"iteration":470,"passed_time":13.82420832,"remaining_time":15.52655244},
{"learn":[0.02778460201],"iteration":471,"passed_time":13.85140483,"remaining_time":15.49479184},
{"learn":[0.02765333042],"iteration":472,"passed_time":13.88199067,"remaining_time":15.46682681},
{"learn":[0.02760642003],"iteration":473,"passed_time":13.90811715,"remaining_time":15.43390215},
{"learn":[0.02756345937],"iteration":474,"passed_time":13.93591108,"remaining_time":15.40284909},
{"learn":[0.02749520139],"iteration":475,"passed_time":13.96486775,"remaining_time":15.37308971},
{"learn":[0.02743405281],"iteration":476,"passed_time":13.99245809,"remaining_time":15.3418356},
{"learn":[0.02736498968],"iteration":477,"passed_time":14.02111887,"remaining_time":15.3117658},
{"learn":[0.02729648421],"iteration":478,"passed_time":14.04817261,"remaining_time":15.27995392},
{"learn":[0.02727379076],"iteration":479,"passed_time":14.07561393,"remaining_time":15.24858175},
{"learn":[0.02722418672],"iteration":480,"passed_time":14.10353825,"remaining_time":15.2177471},
{"learn":[0.02713593771],"iteration":481,"passed_time":14.1328007,"remaining_time":15.18836257},
{"learn":[0.02707995995],"iteration":482,"passed_time":14.1623402,"remaining_time":15.15927513},
{"learn":[0.02703817546],"iteration":483,"passed_time":14.1892634,"remaining_time":15.12739651},
{"learn":[0.02700487496],"iteration":484,"passed_time":14.21685886,"remaining_time":15.09625219},
{"learn":[0.02691725004],"iteration":485,"passed_time":14.24665431,"remaining_time":15.06744921},
{"learn":[0.02685182341],"iteration":486,"passed_time":14.27544708,"remaining_time":15.03758594},
{"learn":[0.02674893201],"iteration":487,"passed_time":14.30509728,"remaining_time":15.00862666},
{"learn":[0.02668935952],"iteration":488,"passed_time":14.33232266,"remaining_time":14.97713063},
{"learn":[0.02664525418],"iteration":489,"passed_time":14.36098721,"remaining_time":14.94714996},
{"learn":[0.02662633192],"iteration":490,"passed_time":14.38930816,"remaining_time":14.91681844},
{"learn":[0.02658791887],"iteration":491,"passed_time":14.41629497,"remaining_time":14.88511757},
{"learn":[0.0265802997],"iteration":492,"passed_time":14.44288243,"remaining_time":14.85302514},
{"learn":[0.02651929498],"iteration":493,"passed_time":14.47074632,"remaining_time":14.82226243},
{"learn":[0.02644228249],"iteration":494,"passed_time":14.50057664,"remaining_time":14.79351759},
{"learn":[0.02636784613],"iteration":495,"passed_time":14.52974868,"remaining_time":14.76409946},
{"learn":[0.0262858925],"iteration":496,"passed_time":14.56928823,"remaining_time":14.74517501},
{"learn":[0.0261549141],"iteration":497,"passed_time":14.5999737,"remaining_time":14.71724256},
{"learn":[0.02609081082],"iteration":498,"passed_time":14.62890956,"remaining_time":14.68754246},
{"learn":[0.02606796933],"iteration":499,"passed_time":14.65848669,"remaining_time":14.65848669},
{"learn":[0.02603473337],"iteration":500,"passed_time":14.688855,"remaining_time":14.63021686},
{"learn":[0.02597781556],"iteration":501,"passed_time":14.7167991,"remaining_time":14.59953377},
{"learn":[0.02589949102],"iteration":502,"passed_time":14.74552615,"remaining_time":14.56963518},
{"learn":[0.02586933565],"iteration":503,"passed_time":14.77337567,"remaining_time":14.53887764},
{"learn":[0.02584942151],"iteration":504,"passed_time":14.80094503,"remaining_time":14.50785701},
{"learn":[0.02582222566],"iteration":505,"passed_time":14.82976358,"remaining_time":14.47806958},
{"learn":[0.02574774515],"iteration":506,"passed_time":14.85916448,"remaining_time":14.44885224},
{"learn":[0.02571450852],"iteration":507,"passed_time":14.88578667,"remaining_time":14.416943},
{"learn":[0.02564903358],"iteration":508,"passed_time":14.91520499,"remaining_time":14.38775176},
{"learn":[0.0255777319],"iteration":509,"passed_time":14.9437191,"remaining_time":14.3576909},
{"learn":[0.0255190485],"iteration":510,"passed_time":14.97333488,"remaining_time":14.32869032},
{"learn":[0.02545767986],"iteration":511,"passed_time":15.00175578,"remaining_time":14.29854847},
{"learn":[0.02541058553],"iteration":512,"passed_time":15.03534214,"remaining_time":14.273317},
{"learn":[0.02538860346],"iteration":513,"passed_time":15.06373146,"remaining_time":14.24313909},
{"learn":[0.0253642981],"iteration":514,"passed_time":15.09172241,"remaining_time":14.21259295},
{"learn":[0.02527006939],"iteration":515,"passed_time":15.12160121,"remaining_time":14.18382749},
{"learn":[0.02524060726],"iteration":516,"passed_time":15.14917604,"remaining_time":14.15290528},
{"learn":[0.02518316983],"iteration":517,"passed_time":15.18113521,"remaining_time":14.12607562},
{"learn":[0.02513303338],"iteration":518,"passed_time":15.21033896,"remaining_time":14.09667252},
{"learn":[0.02509033826],"iteration":519,"passed_time":15.23714935,"remaining_time":14.06506094},
{"learn":[0.02508008705],"iteration":520,"passed_time":15.26423218,"remaining_time":14.03371826},
{"learn":[0.02505176657],"iteration":521,"passed_time":15.29192985,"remaining_time":14.00295492},
{"learn":[0.02499916594],"iteration":522,"passed_time":15.31973094,"remaining_time":13.97229763},
{"learn":[0.02496422931],"iteration":523,"passed_time":15.34644274,"remaining_time":13.94066173},
{"learn":[0.02489830335],"iteration":524,"passed_time":15.3738719,"remaining_time":13.90969362},
{"learn":[0.02486690111],"iteration":525,"passed_time":15.40214598,"remaining_time":13.87950037},
{"learn":[0.02480233606],"iteration":526,"passed_time":15.43429468,"remaining_time":13.852792},
{"learn":[0.02475063627],"iteration":527,"passed_time":15.46293504,"remaining_time":13.82292678},
{"learn":[0.02471772989],"iteration":528,"passed_time":15.48987424,"remaining_time":13.79155155},
{"learn":[0.02468056899],"iteration":529,"passed_time":15.51794878,"remaining_time":13.76119986},
{"learn":[0.02465516412],"iteration":530,"passed_time":15.54665765,"remaining_time":13.73141702},
{"learn":[0.02463353796],"iteration":531,"passed_time":15.58062929,"remaining_time":13.70626787},
{"learn":[0.02457750118],"iteration":532,"passed_time":15.61110937,"remaining_time":13.67802641},
{"learn":[0.02452290478],"iteration":533,"passed_time":15.64081107,"remaining_time":13.6490973},
{"learn":[0.02447202908],"iteration":534,"passed_time":15.6697403,"remaining_time":13.6194939},
{"learn":[0.02442104457],"iteration":535,"passed_time":15.70004843,"remaining_time":13.5910867},
{"learn":[0.02435557591],"iteration":536,"passed_time":15.73001896,"remaining_time":13.56238134},
{"learn":[0.02426702463],"iteration":537,"passed_time":15.76073658,"remaining_time":13.53431283},
{"learn":[0.02419397717],"iteration":538,"passed_time":15.79006039,"remaining_time":13.50504238},
{"learn":[0.02417506128],"iteration":539,"passed_time":15.8175404,"remaining_time":13.47420109},
{"learn":[0.02411549464],"iteration":540,"passed_time":15.84776859,"remaining_time":13.44570385},
{"learn":[0.02409052695],"iteration":541,"passed_time":15.87495176,"remaining_time":13.41462714},
{"learn":[0.02405465973],"iteration":542,"passed_time":15.90434286,"remaining_time":13.385423},
{"learn":[0.02399854653],"iteration":543,"passed_time":15.93157823,"remaining_time":13.35441116},
{"learn":[0.02395048943],"iteration":544,"passed_time":15.96210145,"remaining_time":13.32615809},
{"learn":[0.02391722753],"iteration":545,"passed_time":15.99026492,"remaining_time":13.29593457},
{"learn":[0.02385152367],"iteration":546,"passed_time":16.01875165,"remaining_time":13.26598629},
{"learn":[0.02381797439],"iteration":547,"passed_time":16.04780201,"remaining_time":13.23650823},
{"learn":[0.02379518427],"iteration":548,"passed_time":16.07542094,"remaining_time":13.20585582},
{"learn":[0.02377526171],"iteration":549,"passed_time":16.10297211,"remaining_time":13.175159},
{"learn":[0.02370399788],"iteration":550,"passed_time":16.13172459,"remaining_time":13.14545253},
{"learn":[0.02363523433],"iteration":551,"passed_time":16.16156715,"remaining_time":13.11663421},
{"learn":[0.02355705562],"iteration":552,"passed_time":16.19251182,"remaining_time":13.08870304},
{"learn":[0.02349645344],"iteration":553,"passed_time":16.22151632,"remaining_time":13.05919906},
{"learn":[0.02346158026],"iteration":554,"passed_time":16.25135415,"remaining_time":13.03036504},
{"learn":[0.023416779],"iteration":555,"passed_time":16.27920218,"remaining_time":12.99993843},
{"learn":[0.02328784313],"iteration":556,"passed_time":16.30969149,"remaining_time":12.97162178},
{"learn":[0.02326219153],"iteration":557,"passed_time":16.33688128,"remaining_time":12.94068374},
{"learn":[0.02321871477],"iteration":558,"passed_time":16.36428361,"remaining_time":12.90992678},
{"learn":[0.02316408245],"iteration":559,"passed_time":16.39375591,"remaining_time":12.88080822},
{"learn":[0.02311560656],"iteration":560,"passed_time":16.42152056,"remaining_time":12.8503521},
{"learn":[0.02308809412],"iteration":561,"passed_time":16.44757884,"remaining_time":12.81857568},
{"learn":[0.02302619718],"iteration":562,"passed_time":16.47627051,"remaining_time":12.78886361},
{"learn":[0.02297918591],"iteration":563,"passed_time":16.50571561,"remaining_time":12.7597376},
{"learn":[0.02291882796],"iteration":564,"passed_time":16.53516617,"remaining_time":12.73061466},
{"learn":[0.02287139236],"iteration":565,"passed_time":16.56766961,"remaining_time":12.70383147},
{"learn":[0.02284470824],"iteration":566,"passed_time":16.59719323,"remaining_time":12.6747525},
{"learn":[0.02281438676],"iteration":567,"passed_time":16.6272113,"remaining_time":12.64604803},
{"learn":[0.02275445082],"iteration":568,"passed_time":16.65587497,"remaining_time":12.61631303},
{"learn":[0.02272169245],"iteration":569,"passed_time":16.68339538,"remaining_time":12.58571932},
{"learn":[0.02269437574],"iteration":570,"passed_time":16.71443011,"remaining_time":12.55777674},
{"learn":[0.02264388377],"iteration":571,"passed_time":16.74395132,"remaining_time":12.52869085},
{"learn":[0.02261390529],"iteration":572,"passed_time":16.77181581,"remaining_time":12.49836885},
{"learn":[0.02257801044],"iteration":573,"passed_time":16.80117907,"remaining_time":12.46916774},
{"learn":[0.02256567191],"iteration":574,"passed_time":16.82809698,"remaining_time":12.43815864},
{"learn":[0.02252899634],"iteration":575,"passed_time":16.85603985,"remaining_time":12.40791822},
{"learn":[0.02251633245],"iteration":576,"passed_time":16.88287461,"remaining_time":12.37687341},
{"learn":[0.02250795623],"iteration":577,"passed_time":16.90928434,"remaining_time":12.34553286},
{"learn":[0.022426996],"iteration":578,"passed_time":16.94054543,"remaining_time":12.31773684},
{"learn":[0.02235497623],"iteration":579,"passed_time":16.96783818,"remaining_time":12.28705524},
{"learn":[0.02233759792],"iteration":580,"passed_time":16.99399758,"remaining_time":12.25556796},
{"learn":[0.02229860206],"iteration":581,"passed_time":17.02347798,"remaining_time":12.22648418},
{"learn":[0.02225087907],"iteration":582,"passed_time":17.05144377,"remaining_time":12.1963157},
{"learn":[0.02223141424],"iteration":583,"passed_time":17.07917362,"remaining_time":12.16598669},
{"learn":[0.02220267348],"iteration":584,"passed_time":17.10621484,"remaining_time":12.13517805},
{"learn":[0.02213873277],"iteration":585,"passed_time":17.13517286,"remaining_time":12.10573646},
{"learn":[0.02208658262],"iteration":586,"passed_time":17.16229407,"remaining_time":12.07500418},
{"learn":[0.02208062629],"iteration":587,"passed_time":17.18961775,"remaining_time":12.04442604},
{"learn":[0.02206347275],"iteration":588,"passed_time":17.21770687,"remaining_time":12.01439308},
{"learn":[0.02201740966],"iteration":589,"passed_time":17.24652946,"remaining_time":11.9848764},
{"learn":[0.02199024598],"iteration":590,"passed_time":17.27414905,"remaining_time":11.95452954},
{"learn":[0.02198681879],"iteration":591,"passed_time":17.30030513,"remaining_time":11.92318327},
{"learn":[0.02195283125],"iteration":592,"passed_time":17.32910626,"remaining_time":11.89366989},
{"learn":[0.02191897058],"iteration":593,"passed_time":17.35828395,"remaining_time":11.8644163},
{"learn":[0.02188391553],"iteration":594,"passed_time":17.38809721,"remaining_time":11.83559558},
{"learn":[0.02185861008],"iteration":595,"passed_time":17.41520206,"remaining_time":11.80493563},
{"learn":[0.02181656975],"iteration":596,"passed_time":17.44331918,"remaining_time":11.7749709},
{"learn":[0.02177728343],"iteration":597,"passed_time":17.47147849,"remaining_time":11.74504073},
{"learn":[0.02177292665],"iteration":598,"passed_time":17.49979779,"remaining_time":11.71522356},
{"learn":[0.02176246347],"iteration":599,"passed_time":17.52821214,"remaining_time":11.68547476},
{"learn":[0.02172992922],"iteration":600,"passed_time":17.5625108,"remaining_time":11.65963695},
{"learn":[0.02167441219],"iteration":601,"passed_time":17.59286755,"remaining_time":11.63116493},
{"learn":[0.02163447302],"iteration":602,"passed_time":17.62263799,"remaining_time":11.60230064},
{"learn":[0.02157664704],"iteration":603,"passed_time":17.65408392,"remaining_time":11.57453184},
{"learn":[0.02153272085],"iteration":604,"passed_time":17.68107138,"remaining_time":11.54383999},
{"learn":[0.02146061076],"iteration":605,"passed_time":17.71227303,"remaining_time":11.51590029},
{"learn":[0.02140015976],"iteration":606,"passed_time":17.74209637,"remaining_time":11.48705745},
{"learn":[0.02135541144],"iteration":607,"passed_time":17.77031042,"remaining_time":11.45717382},
{"learn":[0.02132674711],"iteration":608,"passed_time":17.79726229,"remaining_time":11.42648531},
{"learn":[0.02128218431],"iteration":609,"passed_time":17.82625456,"remaining_time":11.39711357},
{"learn":[0.02125613218],"iteration":610,"passed_time":17.85408408,"remaining_time":11.36700279},
{"learn":[0.0211882275],"iteration":611,"passed_time":17.88403915,"remaining_time":11.33824704},
{"learn":[0.02113664152],"iteration":612,"passed_time":17.9132263,"remaining_time":11.30900258},
{"learn":[0.02107064042],"iteration":613,"passed_time":17.94242915,"remaining_time":11.27976816},
{"learn":[0.02104892433],"iteration":614,"passed_time":17.97063882,"remaining_time":11.2499121},
{"learn":[0.02101360034],"iteration":615,"passed_time":17.99876037,"remaining_time":11.22000647},
{"learn":[0.02097128117],"iteration":616,"passed_time":18.02832545,"remaining_time":11.19100267},
{"learn":[0.02095442588],"iteration":617,"passed_time":18.05596176,"remaining_time":11.16080484},
{"learn":[0.02091586186],"iteration":618,"passed_time":18.08531052,"remaining_time":11.13166932},
{"learn":[0.0208861932],"iteration":619,"passed_time":18.11460001,"remaining_time":11.10249678},
{"learn":[0.02084044238],"iteration":620,"passed_time":18.14406896,"remaining_time":11.07343339},
{"learn":[0.02079603833],"iteration":621,"passed_time":18.17339217,"remaining_time":11.04428013},
{"learn":[0.02076875075],"iteration":622,"passed_time":18.20116014,"remaining_time":11.01418519},
{"learn":[0.02073322639],"iteration":623,"passed_time":18.22887227,"remaining_time":10.98406406},
{"learn":[0.02067620029],"iteration":624,"passed_time":18.25942863,"remaining_time":10.95565718},
{"learn":[0.02065517991],"iteration":625,"passed_time":18.28703192,"remaining_time":10.92547913},
{"learn":[0.0206331],"iteration":626,"passed_time":18.31523981,"remaining_time":10.89566898},
{"learn":[0.02061015504],"iteration":627,"passed_time":18.34169223,"remaining_time":10.86482406},
{"learn":[0.02059301631],"iteration":628,"passed_time":18.37054766,"remaining_time":10.83541046},
{"learn":[0.02054451117],"iteration":629,"passed_time":18.39942205,"remaining_time":10.80600978},
{"learn":[0.02049110268],"iteration":630,"passed_time":18.42892832,"remaining_time":10.77698027},
{"learn":[0.02044789263],"iteration":631,"passed_time":18.45668245,"remaining_time":10.74692902},
{"learn":[0.02040498856],"iteration":632,"passed_time":18.4846002,"remaining_time":10.7169799},
{"learn":[0.02040163792],"iteration":633,"passed_time":18.51198615,"remaining_time":10.68673018},
{"learn":[0.02035847213],"iteration":634,"passed_time":18.54453773,"remaining_time":10.6594587},
{"learn":[0.02029395137],"iteration":635,"passed_time":18.57606621,"remaining_time":10.63158506},
{"learn":[0.02025880267],"iteration":636,"passed_time":18.60396964,"remaining_time":10.60163419},
{"learn":[0.02023691946],"iteration":637,"passed_time":18.63110356,"remaining_time":10.57125312},
{"learn":[0.02017131594],"iteration":638,"passed_time":18.66078325,"remaining_time":10.54232043},
{"learn":[0.02015078721],"iteration":639,"passed_time":18.68872598,"remaining_time":10.51240837},
{"learn":[0.02012731344],"iteration":640,"passed_time":18.71650241,"remaining_time":10.48240931},
{"learn":[0.02011984982],"iteration":641,"passed_time":18.74415573,"remaining_time":10.45234852},
{"learn":[0.02011995505],"iteration":642,"passed_time":18.77036274,"remaining_time":10.42149222},
{"learn":[0.02009684597],"iteration":643,"passed_time":18.79869864,"remaining_time":10.3918272},
{"learn":[0.02004917874],"iteration":644,"passed_time":18.82701424,"remaining_time":10.36215512},
{"learn":[0.01998988028],"iteration":645,"passed_time":18.85841786,"remaining_time":10.33417945},
{"learn":[0.01995041011],"iteration":646,"passed_time":18.88867358,"remaining_time":10.30556688},
{"learn":[0.01991221888],"iteration":647,"passed_time":18.91661879,"remaining_time":10.27569416},
{"learn":[0.01987931056],"iteration":648,"passed_time":18.94579699,"remaining_time":10.24649421},
{"learn":[0.01983575492],"iteration":649,"passed_time":18.97469659,"remaining_time":10.21714432},
{"learn":[0.0198168814],"iteration":650,"passed_time":19.00219939,"remaining_time":10.18704698},
{"learn":[0.01978262765],"iteration":651,"passed_time":19.03132439,"remaining_time":10.15782345},
{"learn":[0.01975998394],"iteration":652,"passed_time":19.05949672,"remaining_time":10.12809397},
{"learn":[0.0197225901],"iteration":653,"passed_time":19.08776732,"remaining_time":10.09842124},
{"learn":[0.01970182937],"iteration":654,"passed_time":19.11416327,"remaining_time":10.06776539},
{"learn":[0.01967854322],"iteration":655,"passed_time":19.14174412,"remaining_time":10.03774387},
{"learn":[0.01965464935],"iteration":656,"passed_time":19.16929398,"remaining_time":10.0077136},
{"learn":[0.01964693346],"iteration":657,"passed_time":19.19620261,"remaining_time":9.977357587},
{"learn":[0.01963157729],"iteration":658,"passed_time":19.22352401,"remaining_time":9.947225628},
{"learn":[0.0195938997],"iteration":659,"passed_time":19.2514865,"remaining_time":9.917432439},
{"learn":[0.01954736724],"iteration":660,"passed_time":19.28123984,"remaining_time":9.888563244},
{"learn":[0.01950900752],"iteration":661,"passed_time":19.30952841,"remaining_time":9.858943508},
{"learn":[0.01946990551],"iteration":662,"passed_time":19.33811255,"remaining_time":9.829478023},
{"learn":[0.01943420578],"iteration":663,"passed_time":19.36695635,"remaining_time":9.800146587},
{"learn":[0.01940185151],"iteration":664,"passed_time":19.39477891,"remaining_time":9.770302156},
{"learn":[0.01939298716],"iteration":665,"passed_time":19.42176018,"remaining_time":9.740041891},
{"learn":[0.01936352724],"iteration":666,"passed_time":19.44995116,"remaining_time":9.710395407},
{"learn":[0.01933209551],"iteration":667,"passed_time":19.47803272,"remaining_time":9.680698894},
{"learn":[0.01932018817],"iteration":668,"passed_time":19.50493786,"remaining_time":9.650425158},
{"learn":[0.01930217552],"iteration":669,"passed_time":19.53446019,"remaining_time":9.621450542},
{"learn":[0.01923599583],"iteration":670,"passed_time":19.5667269,"remaining_time":9.593819897},
{"learn":[0.01919871909],"iteration":671,"passed_time":19.59555156,"remaining_time":9.564495402},
{"learn":[0.0191550136],"iteration":672,"passed_time":19.62418271,"remaining_time":9.535078374},
{"learn":[0.01912164307],"iteration":673,"passed_time":19.65091792,"remaining_time":9.504746651},
{"learn":[0.01908641547],"iteration":674,"passed_time":19.67785234,"remaining_time":9.474521499},
{"learn":[0.01905356338],"iteration":675,"passed_time":19.70892334,"remaining_time":9.446288699},
{"learn":[0.0189853685],"iteration":676,"passed_time":19.73998353,"remaining_time":9.418042363},
{"learn":[0.01897543243],"iteration":677,"passed_time":19.76682264,"remaining_time":9.387783024},
{"learn":[0.01892426043],"iteration":678,"passed_time":19.79805524,"remaining_time":9.3596108},
{"learn":[0.01889142609],"iteration":679,"passed_time":19.82645574,"remaining_time":9.330096819},
{"learn":[0.01885708221],"iteration":680,"passed_time":19.85502427,"remaining_time":9.300664819},
{"learn":[0.01884064715],"iteration":681,"passed_time":19.88095195,"remaining_time":9.27000399},
{"learn":[0.01879836136],"iteration":682,"passed_time":19.9110591,"remaining_time":9.24129683},
{"learn":[0.01876835371],"iteration":683,"passed_time":19.93965766,"remaining_time":9.211888624},
{"learn":[0.01872949893],"iteration":684,"passed_time":19.96966385,"remaining_time":9.183130093},
{"learn":[0.01872705999],"iteration":685,"passed_time":19.99647042,"remaining_time":9.152903368},
{"learn":[0.01869063944],"iteration":686,"passed_time":20.02498596,"remaining_time":9.123465221},
{"learn":[0.01866823441],"iteration":687,"passed_time":20.05423134,"remaining_time":9.094360726},
{"learn":[0.01863973493],"iteration":688,"passed_time":20.08217101,"remaining_time":9.064666452},
{"learn":[0.018601951],"iteration":689,"passed_time":20.11135302,"remaining_time":9.035535415},
{"learn":[0.018572643],"iteration":690,"passed_time":20.13961427,"remaining_time":9.005992488},
{"learn":[0.01852530792],"iteration":691,"passed_time":20.16833133,"remaining_time":8.976656139},
{"learn":[0.01850901857],"iteration":692,"passed_time":20.19512726,"remaining_time":8.946470518},
{"learn":[0.01848292293],"iteration":693,"passed_time":20.22272456,"remaining_time":8.916648005},
{"learn":[0.01847150251],"iteration":694,"passed_time":20.25063576,"remaining_time":8.886969651},
{"learn":[0.01843955243],"iteration":695,"passed_time":20.27851508,"remaining_time":8.857282449},
{"learn":[0.01840180729],"iteration":696,"passed_time":20.30921702,"remaining_time":8.828827486},
{"learn":[0.01837323847],"iteration":697,"passed_time":20.33676889,"remaining_time":8.79900316},
{"learn":[0.01836771019],"iteration":698,"passed_time":20.36344088,"remaining_time":8.768806444},
{"learn":[0.01834530807],"iteration":699,"passed_time":20.39100163,"remaining_time":8.739000699},
{"learn":[0.01834535021],"iteration":700,"passed_time":20.4162737,"remaining_time":8.708225159},
{"learn":[0.01831102744],"iteration":701,"passed_time":20.44512122,"remaining_time":8.678983082},
{"learn":[0.01827061516],"iteration":702,"passed_time":20.47273623,"remaining_time":8.649221423},
{"learn":[0.01823669168],"iteration":703,"passed_time":20.50156042,"remaining_time":8.61997427},
{"learn":[0.01819598795],"iteration":704,"passed_time":20.53275929,"remaining_time":8.591721974},
{"learn":[0.01816586084],"iteration":705,"passed_time":20.56349652,"remaining_time":8.563269088},
{"learn":[0.01809726553],"iteration":706,"passed_time":20.5935828,"remaining_time":8.534539972},
{"learn":[0.01808086704],"iteration":707,"passed_time":20.62152784,"remaining_time":8.50492391},
{"learn":[0.01808081979],"iteration":708,"passed_time":20.64654359,"remaining_time":8.474110274},
{"learn":[0.01805083301],"iteration":709,"passed_time":20.67529265,"remaining_time":8.444837844},
{"learn":[0.01800696399],"iteration":710,"passed_time":20.70550865,"remaining_time":8.416163149},
{"learn":[0.01795313179],"iteration":711,"passed_time":20.73572447,"remaining_time":8.387484056},
{"learn":[0.01793187585],"iteration":712,"passed_time":20.76397579,"remaining_time":8.358009892},
{"learn":[0.01792035739],"iteration":713,"passed_time":20.7916949,"remaining_time":8.328325968},
{"learn":[0.01787649767],"iteration":714,"passed_time":20.82274111,"remaining_time":8.299973728},
{"learn":[0.01782418733],"iteration":715,"passed_time":20.85197123,"remaining_time":8.270893616},
{"learn":[0.0177948736],"iteration":716,"passed_time":20.88070656,"remaining_time":8.24161779},
{"learn":[0.01775346581],"iteration":717,"passed_time":20.90927189,"remaining_time":8.212276703},
{"learn":[0.01774771347],"iteration":718,"passed_time":20.93516559,"remaining_time":8.181893645},
{"learn":[0.01772584918],"iteration":719,"passed_time":20.9633428,"remaining_time":8.152411088},
{"learn":[0.01771509873],"iteration":720,"passed_time":20.99244343,"remaining_time":8.123289484},
{"learn":[0.01769209509],"iteration":721,"passed_time":21.02093112,"remaining_time":8.093931928},
{"learn":[0.01766018911],"iteration":722,"passed_time":21.05124075,"remaining_time":8.065274808},
{"learn":[0.01762430607],"iteration":723,"passed_time":21.07897799,"remaining_time":8.035632492},
{"learn":[0.01761661609],"iteration":724,"passed_time":21.10629093,"remaining_time":8.005834491},
{"learn":[0.01758739611],"iteration":725,"passed_time":21.13437414,"remaining_time":7.976334041},
{"learn":[0.01756617093],"iteration":726,"passed_time":21.1617654,"remaining_time":7.946577653},
{"learn":[0.01752613264],"iteration":727,"passed_time":21.19346835,"remaining_time":7.918438725},
{"learn":[0.0175089999],"iteration":728,"passed_time":21.22180359,"remaining_time":7.889038099},
{"learn":[0.01749037065],"iteration":729,"passed_time":21.24944148,"remaining_time":7.859382467},
{"learn":[0.01747738341],"iteration":730,"passed_time":21.27782711,"remaining_time":7.830007512},
{"learn":[0.01744766294],"iteration":731,"passed_time":21.30483875,"remaining_time":7.800132218},
{"learn":[0.01742724195],"iteration":732,"passed_time":21.33392815,"remaining_time":7.771021577},
{"learn":[0.01741976993],"iteration":733,"passed_time":21.36187137,"remaining_time":7.74149562},
{"learn":[0.0173913501],"iteration":734,"passed_time":21.39250026,"remaining_time":7.712942271},
{"learn":[0.01739123899],"iteration":735,"passed_time":21.41902984,"remaining_time":7.682912876},
{"learn":[0.01737549562],"iteration":736,"passed_time":21.44675627,"remaining_time":7.653320078},
{"learn":[0.01736460022],"iteration":737,"passed_time":21.47413603,"remaining_time":7.623609269},
{"learn":[0.01734252813],"iteration":738,"passed_time":21.50360858,"remaining_time":7.594643896},
{"learn":[0.01731053725],"iteration":739,"passed_time":21.53164454,"remaining_time":7.565172404},
{"learn":[0.01729951276],"iteration":740,"passed_time":21.56506189,"remaining_time":7.537585737},
{"learn":[0.01727330283],"iteration":741,"passed_time":21.59333243,"remaining_time":7.508193757},
{"learn":[0.0172181552],"iteration":742,"passed_time":21.62240738,"remaining_time":7.479083037},
{"learn":[0.01718638541],"iteration":743,"passed_time":21.65050932,"remaining_time":7.449637614},
{"learn":[0.01716196766],"iteration":744,"passed_time":21.67779365,"remaining_time":7.419915947},
{"learn":[0.01713505589],"iteration":745,"passed_time":21.70642607,"remaining_time":7.390659813},
{"learn":[0.01712574915],"iteration":746,"passed_time":21.73339992,"remaining_time":7.360843613},
{"learn":[0.01708901838],"iteration":747,"passed_time":21.76199686,"remaining_time":7.331581831},
{"learn":[0.01706387301],"iteration":748,"passed_time":21.79108499,"remaining_time":7.302486426},
{"learn":[0.01704699767],"iteration":749,"passed_time":21.81916685,"remaining_time":7.273055616},
{"learn":[0.01701974466],"iteration":750,"passed_time":21.85016948,"remaining_time":7.244596805},
{"learn":[0.01697922451],"iteration":751,"passed_time":21.88087931,"remaining_time":7.216034666},
{"learn":[0.01697915802],"iteration":752,"passed_time":21.90725247,"remaining_time":7.186044302},
{"learn":[0.01697145867],"iteration":753,"passed_time":21.93448489,"remaining_time":7.156343876},
{"learn":[0.01692970361],"iteration":754,"passed_time":21.96208575,"remaining_time":7.126769547},
{"learn":[0.01691598872],"iteration":755,"passed_time":21.989162,"remaining_time":7.097031121},
{"learn":[0.01689558562],"iteration":756,"passed_time":22.01731274,"remaining_time":7.067644643},
{"learn":[0.01688888122],"iteration":757,"passed_time":22.04502605,"remaining_time":7.038121774},
{"learn":[0.01686098935],"iteration":758,"passed_time":22.07597188,"remaining_time":7.009630071},
{"learn":[0.01682687863],"iteration":759,"passed_time":22.10681169,"remaining_time":6.981098428},
{"learn":[0.01679988939],"iteration":760,"passed_time":22.13650299,"remaining_time":6.952200019},
{"learn":[0.01679988939],"iteration":761,"passed_time":22.16180101,"remaining_time":6.921927351},
{"learn":[0.01678515516],"iteration":762,"passed_time":22.18833053,"remaining_time":6.892050243},
{"learn":[0.01676048723],"iteration":763,"passed_time":22.21706475,"remaining_time":6.862862933},
{"learn":[0.01674406769],"iteration":764,"passed_time":22.24576744,"remaining_time":6.833667122},
{"learn":[0.01671663642],"iteration":765,"passed_time":22.27627891,"remaining_time":6.80502515},
{"learn":[0.01669164975],"iteration":766,"passed_time":22.30498821,"remaining_time":6.775830837},
{"learn":[0.01668260358],"iteration":767,"passed_time":22.33157187,"remaining_time":6.745995668},
{"learn":[0.01666810277],"iteration":768,"passed_time":22.36135091,"remaining_time":6.717128816},
{"learn":[0.01666161651],"iteration":769,"passed_time":22.38887924,"remaining_time":6.687587306},
{"learn":[0.01664469164],"iteration":770,"passed_time":22.41684146,"remaining_time":6.65817989},
{"learn":[0.01662512721],"iteration":771,"passed_time":22.44573284,"remaining_time":6.62905063},
{"learn":[0.01660762266],"iteration":772,"passed_time":22.47354286,"remaining_time":6.599604437},
{"learn":[0.01658627809],"iteration":773,"passed_time":22.50247711,"remaining_time":6.570490732},
{"learn":[0.01656654027],"iteration":774,"passed_time":22.53043289,"remaining_time":6.541093421},
{"learn":[0.01653519838],"iteration":775,"passed_time":22.56429337,"remaining_time":6.513404271},
{"learn":[0.01652483357],"iteration":776,"passed_time":22.59203896,"remaining_time":6.483944259},
{"learn":[0.01649766157],"iteration":777,"passed_time":22.62113668,"remaining_time":6.454874476},
{"learn":[0.01648138063],"iteration":778,"passed_time":22.64891884,"remaining_time":6.425431403},
{"learn":[0.01645894343],"iteration":779,"passed_time":22.67716131,"remaining_time":6.39612242},
{"learn":[0.01645091788],"iteration":780,"passed_time":22.70442127,"remaining_time":6.366540665},
{"learn":[0.01639892818],"iteration":781,"passed_time":22.73467649,"remaining_time":6.33779984},
{"learn":[0.01639883342],"iteration":782,"passed_time":22.760016,"remaining_time":6.307692814},
{"learn":[0.01635984841],"iteration":783,"passed_time":22.78878475,"remaining_time":6.278542737},
{"learn":[0.01634862057],"iteration":784,"passed_time":22.81481742,"remaining_time":6.248644261},
{"learn":[0.0163486751],"iteration":785,"passed_time":22.84268459,"remaining_time":6.219255091},
{"learn":[0.01633581023],"iteration":786,"passed_time":22.87114547,"remaining_time":6.190030476},
{"learn":[0.01631337607],"iteration":787,"passed_time":22.89857278,"remaining_time":6.160529734},
{"learn":[0.01626633343],"iteration":788,"passed_time":22.92771172,"remaining_time":6.131491982},
{"learn":[0.01623842477],"iteration":789,"passed_time":22.95548707,"remaining_time":6.102091499},
{"learn":[0.01619586656],"iteration":790,"passed_time":22.98436356,"remaining_time":6.072986072},
{"learn":[0.01616886151],"iteration":791,"passed_time":23.01263098,"remaining_time":6.043721268},
{"learn":[0.01615275457],"iteration":792,"passed_time":23.04073698,"remaining_time":6.014416842},
{"learn":[0.01614748675],"iteration":793,"passed_time":23.06845344,"remaining_time":5.985014369},
{"learn":[0.01611569292],"iteration":794,"passed_time":23.10260193,"remaining_time":5.957274712},
{"learn":[0.01610637832],"iteration":795,"passed_time":23.13041854,"remaining_time":5.92789621},
{"learn":[0.01608858167],"iteration":796,"passed_time":23.15709231,"remaining_time":5.898230538},
{"learn":[0.01608564408],"iteration":797,"passed_time":23.18267208,"remaining_time":5.86829544},
{"learn":[0.01604519983],"iteration":798,"passed_time":23.21138009,"remaining_time":5.839158195},
{"learn":[0.01601370851],"iteration":799,"passed_time":23.23985873,"remaining_time":5.809964682},
{"learn":[0.01599107242],"iteration":800,"passed_time":23.26852007,"remaining_time":5.780818344},
{"learn":[0.01596084347],"iteration":801,"passed_time":23.29786048,"remaining_time":5.751840867},
{"learn":[0.01594091483],"iteration":802,"passed_time":23.32615123,"remaining_time":5.722604973},
{"learn":[0.01593161138],"iteration":803,"passed_time":23.35383345,"remaining_time":5.69322308},
{"learn":[0.01591146928],"iteration":804,"passed_time":23.38346656,"remaining_time":5.664317987},
{"learn":[0.01588624765],"iteration":805,"passed_time":23.41297043,"remaining_time":5.63537998},
{"learn":[0.01587321542],"iteration":806,"passed_time":23.44048762,"remaining_time":5.605965441},
{"learn":[0.01587322755],"iteration":807,"passed_time":23.46541981,"remaining_time":5.575941341},
{"learn":[0.01585935723],"iteration":808,"passed_time":23.49327653,"remaining_time":5.546620293},
{"learn":[0.01582395341],"iteration":809,"passed_time":23.52138513,"remaining_time":5.517361944},
{"learn":[0.01581494838],"iteration":810,"passed_time":23.54787379,"remaining_time":5.487728911},
{"learn":[0.01578701321],"iteration":811,"passed_time":23.58245599,"remaining_time":5.459977496},
{"learn":[0.01577554974],"iteration":812,"passed_time":23.60936519,"remaining_time":5.430444392},
{"learn":[0.01571881597],"iteration":813,"passed_time":23.63921428,"remaining_time":5.401589504},
{"learn":[0.01570854818],"iteration":814,"passed_time":23.66653584,"remaining_time":5.372158442},
{"learn":[0.01567839992],"iteration":815,"passed_time":23.69490218,"remaining_time":5.342968138},
{"learn":[0.01567196036],"iteration":816,"passed_time":23.72245996,"remaining_time":5.313598742},
{"learn":[0.01565264354],"iteration":817,"passed_time":23.7505112,"remaining_time":5.284343567},
{"learn":[0.01562552664],"iteration":818,"passed_time":23.78091389,"remaining_time":5.255611005},
{"learn":[0.01560660233],"iteration":819,"passed_time":23.80716722,"remaining_time":5.225963535},
{"learn":[0.01559361707],"iteration":820,"passed_time":23.83558899,"remaining_time":5.196797112},
{"learn":[0.01556231156],"iteration":821,"passed_time":23.86566084,"remaining_time":5.167989817},
{"learn":[0.01553038005],"iteration":822,"passed_time":23.89584236,"remaining_time":5.139203035},
{"learn":[0.01551338046],"iteration":823,"passed_time":23.92352828,"remaining_time":5.109879827},
{"learn":[0.01550754832],"iteration":824,"passed_time":23.95057033,"remaining_time":5.080424009},
{"learn":[0.01549350549],"iteration":825,"passed_time":23.97785801,"remaining_time":5.051025779},
{"learn":[0.01546797778],"iteration":826,"passed_time":24.00674305,"remaining_time":5.021966804},
{"learn":[0.01544471839],"iteration":827,"passed_time":24.03406236,"remaining_time":4.992583003},
{"learn":[0.0154340909],"iteration":828,"passed_time":24.06213394,"remaining_time":4.963359352},
{"learn":[0.01541544529],"iteration":829,"passed_time":24.091631,"remaining_time":4.934430446},
{"learn":[0.01540026363],"iteration":830,"passed_time":24.11868388,"remaining_time":4.905003101},
{"learn":[0.01536929904],"iteration":831,"passed_time":24.14750094,"remaining_time":4.87593769},
{"learn":[0.01533539564],"iteration":832,"passed_time":24.17482356,"remaining_time":4.846573271},
{"learn":[0.01533160711],"iteration":833,"passed_time":24.20092628,"remaining_time":4.816970939},
{"learn":[0.01531462215],"iteration":834,"passed_time":24.22966954,"remaining_time":4.787898771},
{"learn":[0.01529336597],"iteration":835,"passed_time":24.25904495,"remaining_time":4.758951403},
{"learn":[0.01526731878],"iteration":836,"passed_time":24.28799225,"remaining_time":4.729919638},
{"learn":[0.01524490814],"iteration":837,"passed_time":24.31714391,"remaining_time":4.700927581},
{"learn":[0.01523649846],"iteration":838,"passed_time":24.34381348,"remaining_time":4.671458844},
{"learn":[0.01522503109],"iteration":839,"passed_time":24.37070242,"remaining_time":4.642038557},
{"learn":[0.01521869945],"iteration":840,"passed_time":24.39953986,"remaining_time":4.612992673},
{"learn":[0.01521222864],"iteration":841,"passed_time":24.42645635,"remaining_time":4.58358682},
{"learn":[0.01519781912],"iteration":842,"passed_time":24.45800063,"remaining_time":4.555048753},
{"learn":[0.01515712283],"iteration":843,"passed_time":24.48799406,"remaining_time":4.526216912},
{"learn":[0.01512085723],"iteration":844,"passed_time":24.51756563,"remaining_time":4.497304938},
{"learn":[0.01509715128],"iteration":845,"passed_time":24.54720228,"remaining_time":4.468403251},
{"learn":[0.01508247746],"iteration":846,"passed_time":24.57994863,"remaining_time":4.440061558},
{"learn":[0.01505486658],"iteration":847,"passed_time":24.60962034,"remaining_time":4.411158363},
{"learn":[0.01503912459],"iteration":848,"passed_time":24.63630616,"remaining_time":4.381722297},
{"learn":[0.01502377032],"iteration":849,"passed_time":24.66516829,"remaining_time":4.352676756},
{"learn":[0.01502374319],"iteration":850,"passed_time":24.69137731,"remaining_time":4.32316712},
{"learn":[0.01501421167],"iteration":851,"passed_time":24.71941707,"remaining_time":4.293983247},
{"learn":[0.01500218031],"iteration":852,"passed_time":24.74693059,"remaining_time":4.264711369},
{"learn":[0.01497341008],"iteration":853,"passed_time":24.77686847,"remaining_time":4.235858076},
{"learn":[0.0149594527],"iteration":854,"passed_time":24.80603424,"remaining_time":4.206871304},
{"learn":[0.01495940708],"iteration":855,"passed_time":24.83207277,"remaining_time":4.177358036},
{"learn":[0.01493434507],"iteration":856,"passed_time":24.86140472,"remaining_time":4.148402421},
{"learn":[0.01490481337],"iteration":857,"passed_time":24.88968763,"remaining_time":4.119272313},
{"learn":[0.01488098189],"iteration":858,"passed_time":24.92059576,"remaining_time":4.09057509},
{"learn":[0.01486557126],"iteration":859,"passed_time":24.94705785,"remaining_time":4.061148952},
{"learn":[0.01484883491],"iteration":860,"passed_time":24.97507131,"remaining_time":4.031980153},
{"learn":[0.01483045372],"iteration":861,"passed_time":25.00497539,"remaining_time":4.00311671},
{"learn":[0.01480273211],"iteration":862,"passed_time":25.03327336,"remaining_time":3.973995887},
{"learn":[0.01477090793],"iteration":863,"passed_time":25.06260243,"remaining_time":3.945039271},
{"learn":[0.01476618515],"iteration":864,"passed_time":25.08948071,"remaining_time":3.915699301},
{"learn":[0.01472651746],"iteration":865,"passed_time":25.11875845,"remaining_time":3.886736296},
{"learn":[0.01472642025],"iteration":866,"passed_time":25.14377753,"remaining_time":3.857119275},
{"learn":[0.01471498184],"iteration":867,"passed_time":25.17126144,"remaining_time":3.827887684},
{"learn":[0.01470744516],"iteration":868,"passed_time":25.19876991,"remaining_time":3.798663819},
{"learn":[0.01469365536],"iteration":869,"passed_time":25.22725882,"remaining_time":3.769590399},
{"learn":[0.01467474687],"iteration":870,"passed_time":25.25437352,"remaining_time":3.740314792},
{"learn":[0.01466602142],"iteration":871,"passed_time":25.28249212,"remaining_time":3.711191504},
{"learn":[0.01465275138],"iteration":872,"passed_time":25.30939621,"remaining_time":3.681893836},
{"learn":[0.01465270756],"iteration":873,"passed_time":25.33609164,"remaining_time":3.652571564},
{"learn":[0.01464842622],"iteration":874,"passed_time":25.36224063,"remaining_time":3.623177233},
{"learn":[0.01462712559],"iteration":875,"passed_time":25.39143889,"remaining_time":3.594221943},
{"learn":[0.01459886683],"iteration":876,"passed_time":25.42213508,"remaining_time":3.565476185},
{"learn":[0.01459481005],"iteration":877,"passed_time":25.44848796,"remaining_time":3.536122472},
{"learn":[0.01459481435],"iteration":878,"passed_time":25.47224428,"remaining_time":3.506418155},
{"learn":[0.01457665823],"iteration":879,"passed_time":25.50007124,"remaining_time":3.477282442},
{"learn":[0.01455970895],"iteration":880,"passed_time":25.52741841,"remaining_time":3.448084893},
{"learn":[0.01455933955],"iteration":881,"passed_time":25.55795951,"remaining_time":3.419318845},
{"learn":[0.01455378639],"iteration":882,"passed_time":25.58694451,"remaining_time":3.390342591},
{"learn":[0.01455365286],"iteration":883,"passed_time":25.61456687,"remaining_time":3.361187508},
{"learn":[0.0145424104],"iteration":884,"passed_time":25.64161488,"remaining_time":3.331961255},
{"learn":[0.01451447108],"iteration":885,"passed_time":25.67258352,"remaining_time":3.30324438},
{"learn":[0.01449007682],"iteration":886,"passed_time":25.70189876,"remaining_time":3.274311793},
{"learn":[0.01447103547],"iteration":887,"passed_time":25.72965063,"remaining_time":3.24518116},
{"learn":[0.01444848898],"iteration":888,"passed_time":25.75650586,"remaining_time":3.215941676},
{"learn":[0.0144484441],"iteration":889,"passed_time":25.78118313,"remaining_time":3.186438365},
{"learn":[0.0144254536],"iteration":890,"passed_time":25.80960349,"remaining_time":3.157403794},
{"learn":[0.01440918095],"iteration":891,"passed_time":25.83822765,"remaining_time":3.128395276},
{"learn":[0.01438828056],"iteration":892,"passed_time":25.86667527,"remaining_time":3.099366465},
{"learn":[0.0143882947],"iteration":893,"passed_time":25.89095973,"remaining_time":3.069845337},
{"learn":[0.01438827499],"iteration":894,"passed_time":25.91595143,"remaining_time":3.040418883},
{"learn":[0.01438829393],"iteration":895,"passed_time":25.94344874,"remaining_time":3.011293157},
{"learn":[0.01438830102],"iteration":896,"passed_time":25.97146104,"remaining_time":2.982230198},
{"learn":[0.0143660649],"iteration":897,"passed_time":26.002164,"remaining_time":2.953475198},
{"learn":[0.01436602518],"iteration":898,"passed_time":26.02825107,"remaining_time":2.924197284},
{"learn":[0.01436591544],"iteration":899,"passed_time":26.05384545,"remaining_time":2.894871717},
{"learn":[0.01434577027],"iteration":900,"passed_time":26.08276645,"remaining_time":2.865919953},
{"learn":[0.01433751568],"iteration":901,"passed_time":26.11032821,"remaining_time":2.836820582},
{"learn":[0.01433754886],"iteration":902,"passed_time":26.13480697,"remaining_time":2.80739344},
{"learn":[0.01433751894],"iteration":903,"passed_time":26.16308,"remaining_time":2.778380177},
{"learn":[0.01433746848],"iteration":904,"passed_time":26.18807979,"remaining_time":2.74902495},
{"learn":[0.01433744383],"iteration":905,"passed_time":26.21264494,"remaining_time":2.719634243},
{"learn":[0.01433744626],"iteration":906,"passed_time":26.23721036,"remaining_time":2.690254204},
{"learn":[0.01433742077],"iteration":907,"passed_time":26.26187436,"remaining_time":2.660894759},
{"learn":[0.01433733642],"iteration":908,"passed_time":26.28709786,"remaining_time":2.631601656},
{"learn":[0.01433724351],"iteration":909,"passed_time":26.3120323,"remaining_time":2.602288909},
{"learn":[0.01432736095],"iteration":910,"passed_time":26.34078899,"remaining_time":2.573359188},
{"learn":[0.01432370643],"iteration":911,"passed_time":26.36738681,"remaining_time":2.544221534},
{"learn":[0.01429694586],"iteration":912,"passed_time":26.39534433,"remaining_time":2.515219011},
{"learn":[0.01429145294],"iteration":913,"passed_time":26.42283748,"remaining_time":2.48617508},
{"learn":[0.01425693547],"iteration":914,"passed_time":26.45370155,"remaining_time":2.457447685},
{"learn":[0.01425184128],"iteration":915,"passed_time":26.48012706,"remaining_time":2.428308595},
{"learn":[0.01423528336],"iteration":916,"passed_time":26.5074463,"remaining_time":2.399256317},
{"learn":[0.01421854504],"iteration":917,"passed_time":26.53578931,"remaining_time":2.370299263},
{"learn":[0.01420747672],"iteration":918,"passed_time":26.56792691,"remaining_time":2.341677997},
{"learn":[0.01419562032],"iteration":919,"passed_time":26.59525595,"remaining_time":2.312630952},
{"learn":[0.01418977315],"iteration":920,"passed_time":26.62195454,"remaining_time":2.283533559},
{"learn":[0.01418964409],"iteration":921,"passed_time":26.64718986,"remaining_time":2.25431758},
{"learn":[0.01418445594],"iteration":922,"passed_time":26.67387835,"remaining_time":2.225231455},
{"learn":[0.01415211464],"iteration":923,"passed_time":26.70412824,"remaining_time":2.196443448},
{"learn":[0.01413489447],"iteration":924,"passed_time":26.73117167,"remaining_time":2.167392297},
{"learn":[0.01410986814],"iteration":925,"passed_time":26.76076365,"remaining_time":2.138549147},
{"learn":[0.01408950329],"iteration":926,"passed_time":26.78814796,"remaining_time":2.10953053},
{"learn":[0.01407567273],"iteration":927,"passed_time":26.81581813,"remaining_time":2.080537614},
{"learn":[0.01404751235],"iteration":928,"passed_time":26.84541338,"remaining_time":2.051694671},
{"learn":[0.01403068351],"iteration":929,"passed_time":26.87437728,"remaining_time":2.022802591},
{"learn":[0.01401307623],"iteration":930,"passed_time":26.90284812,"remaining_time":1.993873814},
{"learn":[0.01397679251],"iteration":931,"passed_time":26.93364206,"remaining_time":1.965115515},
{"learn":[0.0139629526],"iteration":932,"passed_time":26.96271209,"remaining_time":1.936229057},
{"learn":[0.01393794064],"iteration":933,"passed_time":26.99275614,"remaining_time":1.907411034},
{"learn":[0.01392335778],"iteration":934,"passed_time":27.0216356,"remaining_time":1.878509427},
{"learn":[0.01391460078],"iteration":935,"passed_time":27.0499097,"remaining_time":1.849566475},
{"learn":[0.01391460078],"iteration":936,"passed_time":27.07604369,"remaining_time":1.820481059},
{"learn":[0.01390712822],"iteration":937,"passed_time":27.10314302,"remaining_time":1.791465743},
{"learn":[0.01388660541],"iteration":938,"passed_time":27.13090591,"remaining_time":1.762497615},
{"learn":[0.01385985663],"iteration":939,"passed_time":27.16058112,"remaining_time":1.733654114},
{"learn":[0.01385007291],"iteration":940,"passed_time":27.18715562,"remaining_time":1.704614433},
{"learn":[0.01384098097],"iteration":941,"passed_time":27.21466843,"remaining_time":1.675637759},
{"learn":[0.01381696635],"iteration":942,"passed_time":27.24411815,"remaining_time":1.646781266},
{"learn":[0.01381474667],"iteration":943,"passed_time":27.27334127,"remaining_time":1.617910076},
{"learn":[0.01379861773],"iteration":944,"passed_time":27.30204848,"remaining_time":1.589008113},
{"learn":[0.01377749055],"iteration":945,"passed_time":27.32990895,"remaining_time":1.560058228},
{"learn":[0.01377746406],"iteration":946,"passed_time":27.35483758,"remaining_time":1.530946559},
{"learn":[0.01375590985],"iteration":947,"passed_time":27.38386693,"remaining_time":1.50206865},
{"learn":[0.01372974717],"iteration":948,"passed_time":27.41292269,"remaining_time":1.473191841},
{"learn":[0.01370588411],"iteration":949,"passed_time":27.44110212,"remaining_time":1.444268533},
{"learn":[0.01368695095],"iteration":950,"passed_time":27.47012072,"remaining_time":1.415390027},
{"learn":[0.01368686896],"iteration":951,"passed_time":27.49577252,"remaining_time":1.386341472},
{"learn":[0.01366690235],"iteration":952,"passed_time":27.5236371,"remaining_time":1.357409175},
{"learn":[0.01364286631],"iteration":953,"passed_time":27.55817287,"remaining_time":1.328800788},
{"learn":[0.01362327657],"iteration":954,"passed_time":27.58668496,"remaining_time":1.29989615},
{"learn":[0.01360266843],"iteration":955,"passed_time":27.61624657,"remaining_time":1.271040637},
{"learn":[0.01360268509],"iteration":956,"passed_time":27.6412367,"remaining_time":1.241978243},
{"learn":[0.01359813182],"iteration":957,"passed_time":27.66796423,"remaining_time":1.213000519},
{"learn":[0.01358795323],"iteration":958,"passed_time":27.69706425,"remaining_time":1.18412892},
{"learn":[0.01357081132],"iteration":959,"passed_time":27.72539222,"remaining_time":1.155224676},
{"learn":[0.01354969421],"iteration":960,"passed_time":27.75518545,"remaining_time":1.126381095},
{"learn":[0.0135333509],"iteration":961,"passed_time":27.78428957,"remaining_time":1.09750832},
{"learn":[0.01352201125],"iteration":962,"passed_time":27.81201365,"remaining_time":1.068582041},
{"learn":[0.01350997737],"iteration":963,"passed_time":27.83921724,"remaining_time":1.039638818},
{"learn":[0.01350997737],"iteration":964,"passed_time":27.86552422,"remaining_time":1.010666682},
{"learn":[0.01348708051],"iteration":965,"passed_time":27.89373679,"remaining_time":0.9817671333},
{"learn":[0.01347336661],"iteration":966,"passed_time":27.92226216,"remaining_time":0.9528796808},
{"learn":[0.0134575461],"iteration":967,"passed_time":27.95076419,"remaining_time":0.9239922048},
{"learn":[0.01344370105],"iteration":968,"passed_time":27.97990133,"remaining_time":0.8951258423},
{"learn":[0.01343086005],"iteration":969,"passed_time":28.00881957,"remaining_time":0.8662521516},
{"learn":[0.01342894352],"iteration":970,"passed_time":28.03400033,"remaining_time":0.8372667453},
{"learn":[0.01341713404],"iteration":971,"passed_time":28.06212407,"remaining_time":0.8083739443},
{"learn":[0.01340376491],"iteration":972,"passed_time":28.0906816,"remaining_time":0.7794947619},
{"learn":[0.01334491625],"iteration":973,"passed_time":28.12265909,"remaining_time":0.750707532},
{"learn":[0.01334398659],"iteration":974,"passed_time":28.148913,"remaining_time":0.721767},
{"learn":[0.01331955652],"iteration":975,"passed_time":28.17940735,"remaining_time":0.6929362462},
{"learn":[0.01331945135],"iteration":976,"passed_time":28.20537462,"remaining_time":0.6639955131},
{"learn":[0.01331946827],"iteration":977,"passed_time":28.23005663,"remaining_time":0.6350319487},
{"learn":[0.01330640204],"iteration":978,"passed_time":28.25897953,"remaining_time":0.6061681001},
{"learn":[0.0133046394],"iteration":979,"passed_time":28.28460443,"remaining_time":0.5772368252},
{"learn":[0.01327264328],"iteration":980,"passed_time":28.31440079,"remaining_time":0.5483930835},
{"learn":[0.01325949787],"iteration":981,"passed_time":28.34204538,"remaining_time":0.5195079601},
{"learn":[0.01325766157],"iteration":982,"passed_time":28.36808785,"remaining_time":0.4905976536},
{"learn":[0.01324953598],"iteration":983,"passed_time":28.39644949,"remaining_time":0.461730886},
{"learn":[0.01324953355],"iteration":984,"passed_time":28.42158009,"remaining_time":0.4328159404},
{"learn":[0.0132309633],"iteration":985,"passed_time":28.449183,"remaining_time":0.4039437748},
{"learn":[0.01322345949],"iteration":986,"passed_time":28.4761779,"remaining_time":0.3750661729},
{"learn":[0.0132122728],"iteration":987,"passed_time":28.50501166,"remaining_time":0.3462147165},
{"learn":[0.01320358476],"iteration":988,"passed_time":28.53873988,"remaining_time":0.3174177337},
{"learn":[0.0131850673],"iteration":989,"passed_time":28.57065331,"remaining_time":0.2885924576},
{"learn":[0.01318501235],"iteration":990,"passed_time":28.59524269,"remaining_time":0.2596944342},
{"learn":[0.01318501471],"iteration":991,"passed_time":28.62117696,"remaining_time":0.2308159432},
{"learn":[0.01318493039],"iteration":992,"passed_time":28.64686014,"remaining_time":0.2019416123},
{"learn":[0.01316304173],"iteration":993,"passed_time":28.67655736,"remaining_time":0.1730979318},
{"learn":[0.0131579083],"iteration":994,"passed_time":28.70311687,"remaining_time":0.1442367682},
{"learn":[0.01314666383],"iteration":995,"passed_time":28.73091132,"remaining_time":0.115385186},
{"learn":[0.01313163077],"iteration":996,"passed_time":28.75828177,"remaining_time":0.08653444864},
{"learn":[0.01311828817],"iteration":997,"passed_time":28.78770673,"remaining_time":0.05769079505},
{"learn":[0.01310794515],"iteration":998,"passed_time":28.81592888,"remaining_time":0.02884477365},
{"learn":[0.01309582991],"iteration":999,"passed_time":28.84525877,"remaining_time":0}
]}